{"vocab":{"22016":"\u4e0d\u8981\u989d\u5916\u8f93\u51fa\u591a\u4f59\u5185\u5bb9","5124":"vec","56325":"\u8fc7","519":"::","12300":"okes","59405":"\u0936","39950":" \u7b49\u7ea7","13":"\n","56336":"\u8005","530":"ve","56339":"\u70b9","4628":" Array","56349":"\u8868","9245":"\u6c11\u4e3b","56350":"\u6240","2082":" array","7211":" sys","7727":" plt","29235":"ucc","2101":"dict","50744":"orno","24633":"\u8ba9\u5979","37432":"viz","569":" new","6204":"SA","56382":"\u4ef6","57918":"\u9f20","578":"ated","581":" @","54342":" \u8bf7\u5148","1095":" string","32330":"downloads","56907":"\u5bc6","42574":"\u65b0\u4e2d\u56fd","5200":"\u0440\u0430","59473":"\u0987","20471":"umbs","7764":"chain","1625":"lib","56412":"\u7ba1","1116":" list","610":"ory","2147":"ci","56423":"\u6b21","3177":"cover","56433":"\u91d1","2161":"\u4eba\u6c11","8312":" society","4735":"ros","647":" &","8328":"\u201d\uff0c","21129":"viously","5769":" travel","6801":"tee","60562":"\u8a31","2196":"array","17046":"numpy","56472":"\u6d77","56475":"\u4ee3","670":" up","28832":"\u201d\u3001\u201c","39584":"semblies","55461":"ERN","45736":"\u5dee\u8bc4","23721":"iri","1194":"...","27822":"rous","18095":" constants","15536":"libs","1714":"[]","57011":"\u554a","10933":"\u767e\u59d3","1216":"github","4290":"vector","56519":"\u6237","46795":"\u514d\u8d39\u63d0\u4f9b","723":" =>","46292":">(&","44246":"\u81ea\u62c5","19158":"\u7834\u89e3","16599":" Num","7386":" requirements","2270":"ories","29407":"\u0441\u0435","58084":"\u90ed","57062":"\u4eab","19688":"[@","52459":"\u4fb5\u72af\u4e86\u60a8\u7684\u6743\u76ca","6895":"ynch","29427":"ogg","8436":" pd","47862":"\u4e94\u56db","3831":"ana","10998":"encing","5369":" maint","767":"led","6917":"arily","262":" a","263":"on","264":"re","1801":"link","269":"en","5390":")]\\","52498":"\u8868\u4e2d","24858":"esa","289":"ic","10743":"ician","43811":"phis","20773":"otted","1829":" example","1319":" well","6948":"android","14122":" surgery","31018":"]</","54058":"\u5c81\u4e86","14640":"\u653e\u5fc3","307":" and","61236":"\u5bd0","27958":"\u4e94\u4e00","829":" data","42814":"\u7b11\u58f0","8010":"greg","334":" g","11088":":/","13648":"\u6d4f\u89c8\u5668","39250":"\u6b21\u7684","336":" {","34132":"\u6807\u6ce8","21845":"inar","33111":" \u90ed","11609":"\u00e9t","22875":"/*!","63839":"\u953a","352":" for","44541":"]',","3428":" common","57701":"\u7f72","870":"ock","14695":"\u8d5e\u540c\u5176\u89c2\u70b9","56166":" ","16746":"\u5bf9\u6211","56171":"i","50541":"sembling","56174":"s","879":"ian","16752":"igator","15725":"ubs","2927":" float","6005":"\u4e0b\u5217","49013":"\u516c\u5171\u670d\u52a1","375":"ow","46453":"\u8d37\u6b3e\u5e74\u9650","62837":"\u5627","56183":".","56186":",","6518":"agram","1915":"rop","38785":" \u00c9tats","2434":" np","1923":" view","56195":"_","56197":":","56198":"/","907":" file","30093":"\u6d77\u4e0a","9103":" numpy","56208":";","29585":"\u672c\u7ad9\u539f\u521b","1938":" java","403":" as","404":" with","56213":">","19345":" nd","5535":" IP","4514":"\u7533\u8bf7","10147":"\u4e8c\u5341","28581":"ollo","42411":"oner","33195":"\u8bc4\u8bae","1967":" home","442":" H","956":" import","56254":"\u4eba","25536":":]\\","53697":" protoimpl","57792":"\u7070","961":" id","14277":"\u201d\u3002","35271":"]`","13266":"\u6d77\u5916","2002":"iving","57813":"\u76fe","2518":"ched","8153":"fol","478":"ata","56798":"\u514d","48607":"\u91d1\u7684","42978":"quently","491":" from","56306":"\u3002","6133":" py","56311":"\u65e5","27133":"chell","27134":"\u4e2d\u7684\u4efb\u610f\u5185\u5bb9","13569":"hard","64002":"<|EOD|>","6406":" Canada","36872":"IH","1292":" through","13326":"\u516c\u4f17","2062":" around","272":" the","1811":"):","6422":" central","15132":"\u7b2c\u4e94","797":"add","24094":"yclerView","297":" in","301":" to","2864":"cast","56881":"\u4f17","1075":" sub","7741":"ben","575":"sp","57408":"\u70c8","580":"form","324":" (","26694":"zerland","4170":" positive","331":" I","1361":" long","337":" C","18773":" fitness","341":" A","1369":" cons","31322":"UMENT","2138":" di","345":" is","7524":" extract","3943":"PR","56168":"n","56169":"t","56170":"a","56430":"\u7b2c","61039":"\u0ac2","376":"ist","56185":"g","56184":"f","56191":"-","56192":")","56193":"(","56194":"\"","56196":"0","56453":"\u636e","14727":" DC","5513":"enced","8076":" transition","396":" B","56205":"2","3215":" cur","11152":" cycle","22673":"itespace","5009":" General","23442":"uls","34964":"={`","56210":"'","407":" it","56218":"D","56219":"<","924":"ys","1183":"list","13985":"\u4ed6\u4eba","61857":"\u1039","27309":"USH","429":" an","2995":" language","31926":"\u7528\u4eba\u5355\u4f4d","6585":"het","4798":" More","14782":"strings","447":" N","40897":"University","37570":"ThreadPool","2243":"istr","33729":"ennial","24262":"\u6c49\u5b57","24007":" anniversary","5576":" itself","455":" you","22474":" Posted","9163":"\u4f9d\u636e","19404":"\u4ec0\u4e48\u662f","6350":" themselves","2255":" Ad","18640":" proven","16593":"also","4303":" complete","1487":" line","464":" G","469":" The","2780":" above","4071":" Rec","2792":"\u4e5f\u662f","53225":"estimated","1773":" following","502":"all","505":" by","24828":"erk","9217":"adr","769":" my","12547":" directed","1029":" co","3335":" individual","265":"he","16":"\r","43544":"erable","1052":" null","46110":"ahren","2078":"iter","285":"ing","803":"old","16169":"\u0440\u0443","5676":"ped","17198":"umi","303":" of","564":"to","2868":"\u5173\u7cfb","308":" =","8251":" BASIS","1866":" program","35659":"rounded","3661":" women","6488":"\u673a\u5173","12891":"aire","22108":" Miami","14686":"ingly","4961":"\u51fa\u4e86","45408":"ylum","4460":"\u9020\u6210","4092":"abs","7024":" follows","29042":"serts","37491":"serting","20339":"offs","384":" con","14212":"\u6751\u6c11","900":" end","36743":"sembler","648":" .","1672":"using","56201":"=","399":" '","49300":"\u673a\u7b49","1943":"att","8601":" loved","56220":"{","19101":"gressive","4256":"ians","3233":"aged","7089":"\u8eab\u4efd","2488":" control","440":" this","56251":"\uff0c","12988":"\u5e26\u6765\u7684","700":" self","1739":" person","3277":"room","1231":" follow","13013":"OH","13269":" union","57049":"\u6db2","471":" if","3552":" Co","56289":"\u51fa","494":" he","57074":"\u7b11","4084":" defined","1530":" process","1787":" assert","512":"ode","6657":" temp","1030":"ann","6664":"ano","23580":"logist","3100":"\u65c5\u6e38","17438":" crack","35870":"\u0430\u043d\u0438\u0435","56352":"\u4fe1","545":" u","1585":"ives","26677":"bey","56889":"\u677f","8763":"lower","9275":"istent","3065":"last","6734":" conduct","50259":"icaid","604":"ance","6751":" individuals","47725":"\u4e07\u6237","56447":"\u6b63","1673":"ists","20110":"\u641c\u7d22\u5f15\u64ce","4756":" heart","17563":"same","667":" out","46756":"\u8bf7\u591a","1199":" she","7856":" grand","32432":" careers","22194":"\u7ecf\u8d39","1200":" read","693":"://","57013":"\u571f","56314":"\u540e","8902":" growing","1228":" play","5329":" hom","7891":" wife","20697":" speaker","14556":"ushing","9440":" leader","5857":" staff","2280":" None","9966":"AAAA","40175":"\u884c\u4eba","754":" per","58108":"\u5f04","2813":"ording","13567":"idents","42752":"\u6700\u77ed","8962":"atar","259":" t","39685":"REM","17673":"owa","271":" c","3857":"fully","45330":" knees","1303":"org","281":" f","1309":" number","45343":"--)","14117":" Johnson","1322":"ait","37163":"JB","23852":"adder","5425":" career","817":" _","309":" n","53559":"\u6559\u80b2\u57f9\u8bad","3902":" general","56640":"\u5171","840":" use","38226":"\u4e0b\u65ec","19794":" Sciences","17234":"running","5464":" growth","56669":"\u5e26","14181":"semble","364":"ame","59255":"\u9042","6009":" {}","19836":"uction","1406":" state","33676":" poorly","1423":" user","26512":"alling","10133":" unknown","410":"end","57757":"\u9274","4511":"rew","2463":" family","4008":"\u6b22\u8fce","1452":" ->","15281":"ISO","1459":"index","34233":" beating","56256":"!","1478":" ed","5070":"\u6267\u884c","22490":"cii","2525":"icy","996":"ics","485":"ive","50668":" merit","24562":" grat","2546":"ively","2577":" No","25118":"iang","56368":"\u5316","56883":"\u8db3","56385":"\u4f4d","38982":" interpreter","25165":"liest","57933":"\u706d","600":"ize","56414":"\u606f","5216":" ways","15460":"icky","2149":"aving","19046":"edly","33394":"IDI","52339":"\u4f20\u5165","3187":"active","32374":" Published","2679":"hes","632":" #","34942":"logists","3201":" ...","12932":"\u6d41\u52a8","18077":"imm","56989":"\u51cf","39583":" donor","52895":"\u093f\u0924","4260":"zz","683":"ft","2733":"ised","1198":"\u53d1\u5c55","689":"log","56498":"\u683c","11445":"\u8f6c\u6362","41657":"extr","58042":"\u6591","1217":"ily","4294":"la","23753":"\u8f66\u4e3b","13002":"ami","56524":"\u9662","6862":"\u5feb\u4e50","31451":"his","45791":"ceptions","738":" int","6884":"\u5316\u7684","56550":"\u53e3","749":"ph","27887":" Schedule","1778":" day","2806":"ips","27903":" PhD","5888":" bre","260":"in","1807":" ||","56592":"\u8bed","21267":"oust","57110":"\u00e0","280":"is","12571":"oking","19744":"imo","288":" b","20259":"\u7ecf\u7eaa","5412":"eft","7461":"aled","293":" m","9001":" samples","12075":" \u52a0\u597d\u53cb","51504":"\u4f30\u7b97","18224":"pires","311":" h","320":" e","3417":"aging","26976":"\u89e3\u9664","360":" y","17784":" Rh","25977":" \u9875\u6b21","4987":" sample","56698":"\u6df1","23938":"abama","56710":"\u767d","56211":"\u7684","412":"and","1949":"\u7535\u8bdd","5538":" states","420":"ain","56231":"9","56232":"8","56758":"\u8d5b","42944":"WARD","61893":"\u1edf","32720":"BUS","14294":" dtype","56795":"\uff1b","52706":" deceased","487":" [","57836":"\u5211","5620":"ria","56308":"\u5e02","36866":"\u5982\u5bf9","56850":"\u6ee1","13846":"roph","54301":"\u4e0b\u8f7d\u6216\u67e5\u770b\u9644\u4ef6","30237":"mozilla","57392":"\u96f6","49715":"ulong","2612":"ocial","56377":"\u53f8","1600":"ience","52826":"ilen","30300":"\u5e94\u5728\u6388\u6743\u8303\u56f4\u5185\u4f7f\u7528","11869":"\u4e0d\u5f97\u8f6c\u8f7d","56418":"\u91cf","11366":"\u4e4b\u5916","614":"ome","23657":"\u5916\u5730","14950":"icted","34418":" facial","19573":"rangle","51835":"\u662f\u4e16\u754c\u4e0a","56957":"\u65e9","48258":"ofs","20612":" god","6281":"ulate","16012":"encoding","14992":"\u672c\u7f51\u5c06","4241":"\u6765\u81ea","24211":"\u5386\u53f2\u4e0a","12437":"ifi","661":" K","1687":"aut","2712":"\u76f4\u63a5","1184":"url","59041":"\u179c","46255":"\u00edst","57523":"\u6458","60087":"\u560e","15032":" resistance","1720":"\u793e\u4f1a","57531":"\u9f84","32443":"\u515a\u548c","18108":"hom","19652":"\u56fd\u571f","36549":"\u6b64\u9875","21193":"Measure","56521":"\u4e1c","33492":"\u015bci","13026":" featured","19684":"\u5e26\u6765\u4e86","752":"io","17139":"isi","3830":"ias","26885":"lahoma","13577":"ici","21259":"quo","2315":" https","56591":"\u9650","6934":" torch","58650":"\u76f2","56608":"\u5ba2","808":" const","298":"as","48951":"\u7bee\u677f","45372":"\u4f55\u5904","2890":" Christ","34124":"owed","56656":"\u6539","5457":" measure","12625":"oco","5462":" numbers","342":" l","50011":"icus","53595":"\u015b\u0107","13666":"\u5341\u516b","29548":"imeter","877":"\u53ef\u4ee5","1394":"ized","15731":"vet","6534":"iring","392":"ub","402":" de","26518":"auc","20900":"asa","2469":" full","430":"qu","7088":" tf","31674":"meter","56764":"\u4f4e","16321":"GC","15812":" fault","12230":" apart","54219":"\u5229\u5bb3\u5173\u7cfb","57806":"\u4ed3","3536":"number","9681":"isting","466":" \\","18900":" [@","16346":"abb","18907":" pandas","16352":"terior","1517":"go","16369":"occ","1523":" sign","53250":"\u90ae\u7f16","29706":" javafx","53772":"\u4e0d\u4fdd\u8bc1","19470":" arrays","17935":"\u56fd\u4ea7","56351":"\u5fc3","8227":"uzz","39975":"gust","4649":"\\\"/","555":" class","57394":"\u7f29","52791":" sleeves","56389":"\u660e","5714":"WAR","6233":"\u516c\u5f00","25189":" Years","17511":" pi","14957":"stra","629":"og","10366":"hab","2200":"{{","5277":"uy","10913":"\u9a6c\u4e0a","23210":"\u5373\u65f6","1197":"und","40114":"\u5fc3\u52a8","3264":"vis","10434":" laws","3273":"cell","3279":"\u8d44\u6599","57552":"\u70e7","16081":"\u534a\u53e5","3280":"\u514d\u8d39","735":"]\\","36073":"\u4f4e\u7684","30954":"\u5747\u8f6c\u8f7d\u81ea\u5176\u5b83\u5a92\u4f53","56556":"\u8eab","44782":"```<","1775":"lear","16112":"oped","771":" their","2819":"ently","28940":"ows","12057":" nn","287":"ed","10023":"\u5fd7\u613f","295":"et","37680":"oop","58727":"\u03b8","33137":" ${{","7027":"\u72ec\u7acb","63353":"\ufe0e","13692":"ugs","41856":"\u5b89\u5fc3","893":" x","23939":" \u03c0","50058":"\u5965\u65af\u5361","59787":"\u03c2","1933":"\u7814\u7a76","22928":"\u7f51\u8baf","18320":"\u4e2a\u4f53","58259":"\u03c0","60312":"\u6363","56731":"\u914d","2971":" days","8608":"\u534f\u8c03","932":"](","42926":"iten","6576":"\u516c\u544a","28594":"inform","21940":"\u516c\u6b63","56244":"\u3001","23479":"pytest","17849":" Cart","56260":"?","12234":" justice","467":"int","10721":"los","57312":"\u786c","5598":" vector","6633":" fem","15862":" faces","59384":"\u50f5","5627":"otype","3581":" API","56323":"\u597d","8201":" \u5171","1568":" years","30250":"\u60a8\u7684\u8bc4\u8bba","16442":" privacy","14908":" \u9605\u8bfb\u6743\u9650","38464":"variance","32835":"adients","5712":"\u4ee3\u7406","12368":" tum","12899":"ocks","51816":"\u00eate","57972":"\u5fe7","3193":" q","9867":"\u5e73\u8861","1168":"np","14502":" gam","2233":" range","33978":" \u70b9\u9001","702":" `","16602":"atern","9951":" smooth","48870":"\u51e0\u5bb6","54508":"\u6b64\u65b0\u95fb","2285":"ety","55559":"=====","282":" p","47917":"\u5bf9\u5979","57678":"\u6562","11636":" boot","1946":" local","3500":" members","34222":"mart","427":"up","50100":"sided","44474":"\u5b66\u58eb","5053":"ams","47554":"\u6bcf\u4e2a\u6708\u5e94\u8fd8\u8d37","1504":"ince","60397":"\u6d31","1009":" her","39931":" reviewer"},"steps":{"1002650":{"top":[[[[29427,0.0762],[27133,0.06286],[375,0.04098],[57062,0.0362],[8153,0.01657],[14122,0.01001],[6005,0.00952],[6801,0.00707],[5369,0.0065],[29585,0.00598]],[[16752,0.1838],[42411,0.0612],[52459,0.04762],[28581,0.03454],[50744,0.02036],[11088,0.01941],[46292,0.0178],[10743,0.01704],[33195,0.01308],[55461,0.01065]],[[53697,0.20812],[20773,0.06627],[22016,0.03332],[54342,0.03258],[13648,0.02531],[63839,0.01557],[5200,0.01497],[59405,0.01304],[59473,0.01146],[38785,0.01091]]],[[[767,0.08636],[10147,0.01041],[27958,0.00905],[56336,0.00854],[56254,0.00797],[39250,0.00714],[57011,0.0069],[2518,0.00681],[49013,0.00667],[8312,0.00654]],[[52498,0.14321],[14640,0.10671],[44246,0.05971],[8328,0.02412],[46453,0.02372],[4735,0.01772],[62837,0.01587],[29407,0.01392],[14277,0.01209],[28832,0.0119]],[[47862,0.19618],[1319,0.06243],[27958,0.06004],[5390,0.03153],[19688,0.01775],[56325,0.00967],[46795,0.00794],[50541,0.00633],[3177,0.00589],[45736,0.00463]]],[[[670,0.01033],[56254,0.00697],[56519,0.00691],[1829,0.00688],[56382,0.00676],[56412,0.00594],[21129,0.00551],[56311,0.00547],[56433,0.00536],[578,0.00524]],[[6917,0.15325],[57813,0.01972],[23721,0.01772],[27822,0.01675],[22875,0.01206],[56349,0.0115],[11609,0.0103],[7386,0.01006],[3831,0.00744],[6204,0.00644]],[[39584,0.10951],[35271,0.07459],[32330,0.05785],[25536,0.04936],[39950,0.04243],[31018,0.0133],[44541,0.01],[19688,0.00815],[14695,0.00764],[27134,0.00696]]],[[[2270,0.08544],[610,0.01666],[478,0.01302],[43811,0.01279],[1625,0.01178],[1801,0.00929],[12300,0.00765],[7764,0.00614],[578,0.00612],[24858,0.00566]],[[56798,0.04479],[56174,0.042],[7211,0.02109],[879,0.01779],[56423,0.01627],[5535,0.01493],[6204,0.01224],[269,0.00988],[1194,0.00897],[56306,0.00802]],[[24633,0.10525],[6895,0.02978],[29235,0.02244],[57701,0.02061],[10998,0.01874],[870,0.01602],[9245,0.01405],[8010,0.01375],[2147,0.01175],[34132,0.01086]]],[[[2270,0.35208],[264,0.01015],[610,0.01005],[1625,0.00977],[578,0.00732],[24858,0.00673],[767,0.00563],[48607,0.00537],[478,0.00486],[1801,0.00336]],[[56475,0.12637],[1923,0.09137],[56195,0.0212],[56171,0.01747],[56183,0.01079],[647,0.01055],[56798,0.00944],[307,0.0083],[56472,0.00775],[13266,0.00733]],[[5124,0.07163],[57918,0.06885],[58084,0.01884],[56907,0.01622],[57792,0.01441],[56350,0.01405],[33111,0.01302],[60562,0.01087],[42574,0.01023],[16746,0.00953]]],[[[530,0.03474],[61236,0.01497],[2270,0.01486],[723,0.00819],[2002,0.00693],[478,0.00685],[21845,0.00588],[15725,0.00534],[54058,0.00469],[42978,0.0045]],[[56186,0.11961],[56183,0.07934],[56472,0.04979],[307,0.04138],[56166,0.02549],[403,0.02258],[404,0.01962],[30093,0.01954],[2161,0.01906],[1923,0.01697]],[[57792,0.04711],[19158,0.04018],[3428,0.02783],[1967,0.02082],[4290,0.01672],[10933,0.01574],[491,0.01477],[442,0.01274],[56339,0.01221],[5769,0.01035]]],[[[530,0.0275],[61236,0.02006],[2270,0.01597],[478,0.00738],[723,0.0073],[21845,0.00711],[2002,0.00678],[42814,0.00579],[15725,0.0054],[42978,0.00534]],[[56166,0.05007],[56198,0.03349],[519,0.02898],[56186,0.01818],[307,0.01697],[56195,0.01561],[13,0.01472],[403,0.0137],[56183,0.01324],[1923,0.01263]],[[4514,0.0472],[18095,0.02848],[20471,0.01915],[2101,0.01892],[334,0.01888],[3428,0.0157],[13,0.01561],[6518,0.01526],[961,0.01388],[263,0.013]]],[[[530,0.03098],[61236,0.02092],[2270,0.01395],[21845,0.0085],[723,0.00805],[478,0.00793],[2002,0.0074],[15725,0.0063],[42814,0.00561],[54058,0.00463]],[[56198,0.06474],[519,0.05693],[37432,0.02782],[2196,0.02619],[289,0.01509],[15536,0.01409],[56213,0.01298],[1915,0.01165],[403,0.01068],[307,0.00874]],[[2434,0.18042],[9103,0.07381],[1216,0.04302],[2196,0.03781],[1714,0.0298],[581,0.02682],[6948,0.01825],[1116,0.01767],[13,0.01327],[4628,0.01228]]],[[[56166,0.02476],[1938,0.02378],[956,0.02107],[569,0.01072],[1095,0.0098],[336,0.00949],[829,0.00907],[907,0.00821],[262,0.00808],[491,0.00764]],[[403,0.69433],[56183,0.05978],[13,0.04684],[956,0.04584],[56186,0.01815],[56197,0.00933],[352,0.00461],[56166,0.00454],[56208,0.00446],[2082,0.00388]],[[2434,0.72136],[9103,0.23749],[6133,0.00522],[13,0.00255],[7727,0.00215],[8436,0.00193],[16599,0.00079],[2927,0.00077],[17046,0.00074],[19345,0.00067]]]],"tgt":{"13":{"p":[[1e-06,0.0,0.0],[1.4e-05,1e-06,6e-06],[0.000158,2e-05,1e-06],[8.2e-05,0.000865,3.7e-05],[0.000126,0.001182,0.001186],[7.8e-05,0.009995,0.009237],[4.2e-05,0.014715,0.015608],[5.2e-05,0.002943,0.013274],[0.004438,0.046839,0.002553]],"r":[[19224,43650,36559],[6293,15497,9711],[985,4425,19299],[1717,149,2104],[725,102,115],[1938,11,12],[3525,7,7],[2836,39,9],[28,3,4]]},"403":{"p":[[0.0,1e-06,0.0],[0.000164,0.0,5e-06],[0.000167,2.2e-05,0.0],[2.8e-05,0.000627,2e-06],[1.1e-05,0.001221,0.000117],[9e-06,0.022577,0.002862],[7e-06,0.013698,0.002995],[1e-05,0.010678,0.000363],[0.003139,0.694328,8.9e-05]],"r":[[46956,18003,58593],[890,20733,10488],[932,4044,37128],[4783,210,13712],[7192,97,978],[11967,6,51],[13981,8,47],[11264,9,257],[41,1,72]]},"956":{"p":[[0.0,0.0,0.0],[1e-06,2e-05,1e-06],[8e-06,2e-06,0.0],[2e-06,0.000268,1e-06],[2e-06,0.000215,4.5e-05],[5e-06,0.003352,0.000259],[4e-06,0.005946,0.006558],[4e-06,0.001442,0.004525],[0.021072,0.045844,0.00037]],"r":[[63598,52499,50751],[25040,2594,29247],[13911,16670,41624],[24973,498,17944],[21976,515,2139],[17674,34,467],[19759,22,18],[18915,86,20],[3,4,21]]},"1938":{"p":[[7e-06,2e-06,0.0],[2.5e-05,1e-06,0.0],[4e-06,0.0,0.0],[1e-06,6e-06,0.0],[0.0,3e-06,0.0],[3e-06,9.4e-05,1e-06],[3e-06,0.000217,3.1e-05],[3e-06,1.1e-05,0.000607],[0.023781,4e-06,2.7e-05]],"r":[[6731,11992,26118],[4283,17079,45881],[21307,47188,43589],[39350,9303,60090],[42062,11770,26028],[23691,847,14375],[23706,558,2396],[22670,5971,159],[2,1815,166]]},"2434":{"p":[[5.1e-05,2e-06,0.0],[2.8e-05,0.0,0.0],[4e-06,1e-06,0.0],[2e-06,1e-05,0.0],[1e-06,3.6e-05,4.9e-05],[5e-06,2.5e-05,1.2e-05],[4e-06,1.4e-05,0.000279],[5e-06,0.002149,0.180421],[0.00011,0.002378,0.721361]],"r":[[1831,12470,58284],[3982,50283,49398],[19337,21142,47108],[28364,7196,34488],[28060,2411,2042],[18077,2355,4533],[18928,4518,456],[18165,50,1],[1163,16,1]]},"6133":{"p":[[0.0,1e-06,0.0],[1.2e-05,1e-06,3e-06],[1.4e-05,1.6e-05,1.1e-05],[5e-06,0.000114,0.0],[3e-06,0.000902,0.0],[1e-06,0.003922,4e-06],[1e-06,0.000167,1e-05],[1e-06,0.000286,0.000734],[0.000579,9.4e-05,0.005217]],"r":[[24762,18851,55716],[7135,18007,13932],[9218,5142,5047],[16707,1164,30245],[15877,130,25162],[34504,27,8342],[35942,686,5173],[33834,416,130],[269,169,3]]},"9103":{"p":[[5.7e-05,0.0,0.0],[0.000105,1e-06,5e-06],[2.7e-05,3.3e-05,1e-05],[5.4e-05,0.000181,0.0],[9e-06,4.7e-05,1.4e-05],[1.7e-05,7.8e-05,1.1e-05],[2.2e-05,2.5e-05,2.5e-05],[2.6e-05,0.001522,0.073809],[0.001539,0.001305,0.237491]],"r":[[1671,24249,36297],[1319,16371,10706],[5663,2950,5120],[2630,738,37228],[8606,1978,4802],[7531,1002,4722],[6102,3064,2769],[5451,81,2],[94,23,2]]},"56166":{"p":[[2e-06,6e-06,0.0],[0.000978,3e-06,0.000144],[0.000473,9e-06,1e-06],[4.8e-05,0.001347,0.000151],[1.8e-05,0.004164,0.000135],[6.1e-05,0.025486,0.001615],[3.9e-05,0.050068,0.0095],[4.1e-05,0.001086,0.001105],[0.024763,0.004539,0.000434]],"r":[[14320,6141,24098],[126,8285,685],[265,8010,21382],[2936,83,684],[4943,22,858],[2495,5,91],[3752,1,14],[3578,116,91],[1,8,18]]},"56183":{"p":[[4e-06,3e-06,0.0],[0.00098,9e-06,4e-06],[7.4e-05,3.9e-05,1e-06],[3.1e-05,0.005278,4e-06],[3e-05,0.010786,2.6e-05],[2.1e-05,0.079336,0.002783],[1.5e-05,0.01324,0.002541],[1.6e-05,0.005455,0.000149],[0.005767,0.05978,6.6e-05]],"r":[[9788,8788,56521],[125,4548,12934],[2286,2615,24026],[4346,17,8535],[3101,5,3223],[6639,2,52],[8177,9,60],[8065,16,531],[16,2,95]]}}},"16780":{"top":[[[[23442,0.00178],[26694,0.00094],[7741,0.00078],[3943,0.00075],[40897,0.00073],[16593,0.00072],[36872,0.00071],[11152,0.00068],[24828,0.00066],[27309,0.00059]],[[13326,0.00176],[34964,0.00096],[13985,0.00087],[19404,0.00081],[14782,0.00076],[24262,0.00076],[61039,0.00063],[31322,0.0005],[61857,0.00048],[2243,0.00046]],[[22673,0.00098],[56881,0.00095],[2864,0.00091],[24094,0.00087],[33729,0.00072],[6585,0.00062],[37570,0.0006],[31926,0.00059],[53225,0.00057],[24007,0.00055]]],[[[575,0.00163],[9163,0.00159],[56193,0.0012],[1183,0.00114],[56218,0.00105],[580,0.00093],[56184,0.0008],[56169,0.00077],[1116,0.00075],[56430,0.00072]],[[5576,0.0115],[6350,0.00218],[1773,0.00177],[2780,0.00173],[2995,0.00169],[7524,0.00167],[1967,0.00149],[2062,0.00119],[1487,0.00111],[8076,0.00098]],[[1319,0.00507],[7524,0.00173],[56453,0.00135],[2780,0.00131],[797,0.00107],[56196,0.00102],[3215,0.00102],[429,0.00095],[18773,0.00089],[15132,0.00081]]],[[[56193,0.00825],[13,0.00576],[56197,0.0052],[924,0.00482],[64002,0.00408],[56186,0.0035],[505,0.00313],[9163,0.00236],[1811,0.00228],[56185,0.00222]],[[924,0.00277],[56183,0.00255],[1075,0.00248],[56166,0.00239],[56186,0.00232],[1967,0.00227],[56191,0.0022],[403,0.00192],[1369,0.00141],[307,0.00135]],[[1319,0.00419],[2255,0.00131],[1369,0.00123],[56453,0.00123],[376,0.00119],[2792,0.00088],[6422,0.00084],[797,0.00083],[56219,0.00075],[2138,0.00073]]],[[[13,0.05255],[307,0.01972],[64002,0.01589],[56186,0.01407],[56193,0.00841],[56191,0.00686],[56166,0.0068],[56210,0.00576],[56183,0.005],[341,0.00406]],[[13,0.01697],[56166,0.00936],[56186,0.00867],[307,0.00654],[56183,0.00537],[56191,0.0034],[924,0.00223],[1292,0.0022],[352,0.00202],[403,0.00199]],[[2255,0.00317],[1319,0.00214],[4170,0.00143],[464,0.00102],[1361,0.0009],[272,0.00084],[337,0.00082],[4798,0.00078],[13,0.00075],[6406,0.00075]]],[[[13,0.01738],[64002,0.00267],[56166,0.00262],[307,0.00245],[56210,0.0018],[56191,0.00174],[2255,0.00126],[924,0.00123],[22474,0.00122],[502,0.00121]],[[13,0.01078],[56166,0.00798],[56191,0.00317],[464,0.00248],[307,0.00204],[56210,0.00193],[396,0.00191],[447,0.0017],[56183,0.00167],[924,0.00165]],[[2255,0.0024],[5009,0.00143],[57408,0.00101],[464,0.00094],[22474,0.00092],[5513,0.00082],[18640,0.0008],[4071,0.00076],[4170,0.00071],[14727,0.00069]]],[[[13,0.06862],[56166,0.01335],[307,0.00761],[56191,0.00667],[64002,0.00609],[56186,0.0051],[56193,0.00302],[56194,0.00251],[341,0.00248],[56183,0.00227]],[[13,0.04964],[56166,0.018],[56191,0.00764],[307,0.00664],[56186,0.00607],[64002,0.00307],[56183,0.00296],[324,0.00259],[56170,0.00257],[331,0.00233]],[[13,0.01972],[56166,0.00717],[56191,0.00217],[64002,0.00197],[307,0.0019],[331,0.00148],[13569,0.00148],[464,0.00138],[341,0.00134],[56170,0.0013]]],[[[13,0.03895],[56166,0.01494],[56191,0.00882],[307,0.00462],[64002,0.00368],[341,0.00308],[56186,0.00305],[56193,0.00263],[13569,0.00245],[56194,0.00241]],[[56166,0.02462],[13,0.02338],[56191,0.00876],[307,0.00329],[464,0.00302],[56186,0.0029],[56170,0.00265],[324,0.00263],[331,0.00248],[341,0.00243]],[[56166,0.00836],[13,0.00829],[464,0.00205],[56191,0.00162],[341,0.00161],[56168,0.00157],[13569,0.00156],[331,0.00153],[447,0.00145],[272,0.00142]]],[[[13,0.04349],[56166,0.02302],[56191,0.0189],[56193,0.00851],[56183,0.00697],[307,0.00532],[56186,0.00529],[56194,0.00527],[56197,0.00387],[56192,0.00372]],[[56166,0.03447],[13,0.02128],[56191,0.01727],[56183,0.01024],[324,0.00591],[56186,0.00534],[56193,0.00468],[56195,0.00362],[56198,0.00347],[272,0.00325]],[[56166,0.01381],[13,0.00762],[272,0.00577],[56191,0.00331],[262,0.0028],[331,0.00247],[4303,0.00242],[469,0.00239],[447,0.00236],[56205,0.00226]]],[[[56183,0.04496],[13,0.04133],[307,0.02927],[56166,0.02891],[56186,0.02428],[56191,0.01494],[297,0.01347],[56193,0.01243],[345,0.00973],[56194,0.00958]],[[56183,0.06296],[56166,0.05453],[56186,0.03678],[307,0.02346],[297,0.02132],[272,0.02119],[403,0.01956],[13,0.01571],[324,0.01292],[56195,0.01265]],[[272,0.0886],[262,0.03982],[56166,0.02494],[429,0.01566],[407,0.01191],[331,0.01152],[297,0.01005],[455,0.00884],[301,0.00781],[13,0.00731]]]],"tgt":{"13":{"p":[[8e-06,6e-06,3e-06],[0.000275,0.000365,0.000197],[0.005764,0.001082,0.000479],[0.052552,0.016974,0.000751],[0.017381,0.010783,0.000616],[0.068621,0.049643,0.01972],[0.038952,0.023383,0.008291],[0.043492,0.021281,0.007615],[0.041329,0.015706,0.007312]],"r":[[31845,40934,50766],[123,67,286],[2,13,38],[1,1,9],[1,1,14],[1,1,1],[1,2,2],[1,2,2],[2,8,10]]},"403":{"p":[[0.0,3.6e-05,1e-06],[5.4e-05,0.00038,3.1e-05],[0.000352,0.001918,4.9e-05],[0.000497,0.001992,4.8e-05],[6.6e-05,0.00041,1.5e-05],[0.000122,0.000225,7.9e-05],[0.000123,0.000307,9.4e-05],[0.000322,0.001386,0.000331],[0.002417,0.019561,0.003838]],"r":[[63996,5908,61565],[3335,63,7570],[173,8,3972],[132,10,4367],[2498,114,16423],[908,370,1985],[919,242,1531],[248,40,232],[36,7,18]]},"956":{"p":[[5e-06,1e-06,0.0],[0.000236,1.4e-05,1.2e-05],[0.000241,9.7e-05,2.9e-05],[0.000186,6.4e-05,9.1e-05],[0.000652,0.000496,0.00031],[0.000116,0.000105,0.000115],[0.000119,0.00011,0.000119],[0.000251,0.000318,0.000265],[0.000645,0.000956,0.000316]],"r":[[44115,63247,64123],[174,18495,21763],[310,1274,8432],[555,2646,1665],[37,84,83],[989,1128,1064],[970,1099,1027],[346,258,325],[119,94,343]]},"1938":{"p":[[1e-05,4e-06,1.5e-05],[6e-06,1.2e-05,6.3e-05],[1.1e-05,7e-06,1.4e-05],[3e-06,4e-06,3e-06],[2e-06,3e-06,2e-06],[4e-06,5e-06,7e-06],[4e-06,5e-06,7e-06],[6e-06,1.1e-05,1.2e-05],[1.2e-05,4e-05,2.1e-05]],"r":[[28558,49658,18248],[36691,21609,2580],[18892,30500,19016],[36283,31412,43945],[48218,43629,53371],[30529,27462,27351],[34884,28400,26987],[24956,15644,15961],[8657,2349,5034]]},"2434":{"p":[[7.3e-05,4e-06,1.6e-05],[1.7e-05,6e-06,7e-05],[5.1e-05,1e-05,0.000107],[2.1e-05,6e-06,2.1e-05],[1.8e-05,1.1e-05,1.5e-05],[1.7e-05,1.5e-05,1.9e-05],[1.7e-05,1.8e-05,2.2e-05],[2.4e-05,3e-05,4e-05],[2.8e-05,4e-05,3.9e-05]],"r":[[1767,48845,16952],[15016,33528,2157],[3389,22413,993],[7884,25998,11565],[12818,19361,16638],[11360,13049,11764],[11407,11147,10094],[7104,5451,4620],[3748,2348,2846]]},"6133":{"p":[[1.8e-05,7e-06,0.0],[3e-06,2.4e-05,5e-06],[3e-05,6.1e-05,2.8e-05],[2.1e-05,1.2e-05,1.3e-05],[2.5e-05,2.3e-05,1.3e-05],[1.7e-05,1.6e-05,1.8e-05],[2.3e-05,2.5e-05,2.8e-05],[2.6e-05,3.5e-05,5.1e-05],[3.8e-05,5.5e-05,0.00012]],"r":[[14975,36741,64105],[47962,10350,36798],[6828,2800,8564],[7844,15704,17821],[9092,9648,18830],[11353,12060,12273],[8777,7728,7949],[6304,4544,3385],[2774,1749,937]]},"9103":{"p":[[8e-06,7e-06,2e-06],[2.1e-05,2e-05,1.6e-05],[3.9e-05,1.8e-05,1.6e-05],[1.3e-05,9e-06,1.7e-05],[1e-05,1.1e-05,2.1e-05],[4e-06,4e-06,6e-06],[3e-06,4e-06,7e-06],[4e-06,7e-06,1.6e-05],[4e-06,1.2e-05,1.7e-05]],"r":[[32870,37818,54146],[12445,12424,15966],[4795,13252,16156],[12912,19392,14082],[22610,19484,12367],[33202,32406,28096],[36542,33037,26980],[30410,22433,12805],[19534,6895,6112]]},"56166":{"p":[[5e-06,9.3e-05,8e-06],[0.000182,0.000254,0.000216],[0.001876,0.002392,0.000634],[0.006804,0.009358,0.000608],[0.002623,0.007975,0.000345],[0.013351,0.017996,0.007168],[0.014943,0.024623,0.008359],[0.023016,0.034474,0.013811],[0.028909,0.054527,0.02494]],"r":[[44095,977,32858],[305,139,238],[13,4,19],[7,2,23],[3,2,66],[2,2,2],[2,1,1],[2,1,1],[4,2,3]]},"56183":{"p":[[4e-06,3e-06,1e-06],[8.2e-05,0.000292,2.5e-05],[0.001589,0.002547,4.8e-05],[0.004997,0.005372,3e-05],[0.000631,0.001673,9e-06],[0.002265,0.002957,0.000514],[0.001767,0.002174,0.000312],[0.00697,0.010236,0.000932],[0.044959,0.062961,0.005093]],"r":[[48114,51091,61245],[1608,107,9961],[17,2,4131],[9,5,8017],[40,9,25271],[10,7,90],[14,12,192],[5,4,45],[1,1,16]]}}},"33550":{"top":[[[[13013,0.00527],[23442,0.0034],[2518,0.00282],[7741,0.00251],[27309,0.00241],[36872,0.00237],[26694,0.00232],[9217,0.00188],[24828,0.00168],[14686,0.00168]],[[13326,0.00321],[2243,0.00166],[7089,0.00164],[16169,0.00157],[14212,0.00157],[31322,0.00152],[61039,0.00138],[43544,0.00133],[19404,0.00131],[6350,0.00122]],[[5676,0.00427],[57074,0.00269],[24007,0.00204],[12891,0.00202],[35659,0.00193],[24094,0.00189],[20339,0.00181],[46110,0.00169],[56881,0.00162],[22108,0.00146]]],[[[1183,0.01094],[1739,0.00866],[1943,0.00594],[13,0.00453],[3335,0.00274],[265,0.00268],[900,0.00259],[494,0.00254],[1530,0.00241],[442,0.00223]],[[2868,0.0094],[56183,0.00738],[13,0.00639],[1116,0.00637],[8601,0.00553],[1866,0.00402],[56166,0.00395],[1773,0.00285],[56195,0.00284],[56289,0.00281]],[[1319,0.05135],[37491,0.01149],[29042,0.01148],[1231,0.00752],[429,0.00692],[3215,0.00421],[7524,0.00337],[3661,0.00311],[1052,0.00309],[6488,0.00275]]],[[[13,0.02417],[56166,0.01225],[399,0.01189],[1530,0.01086],[900,0.01077],[56186,0.0095],[64002,0.00861],[262,0.00787],[2488,0.00654],[56183,0.00641]],[[13,0.03919],[56166,0.01566],[307,0.00849],[56183,0.00768],[64002,0.00653],[1530,0.00624],[648,0.00621],[1361,0.0058],[352,0.00524],[505,0.00488]],[[1319,0.06757],[37491,0.01029],[262,0.00649],[429,0.00518],[7024,0.0044],[494,0.00395],[384,0.003],[564,0.00288],[1231,0.00284],[399,0.00258]]],[[[13,0.06662],[56166,0.02208],[64002,0.01235],[900,0.00867],[56201,0.00839],[262,0.00809],[399,0.00708],[307,0.00596],[1029,0.00575],[797,0.00569]],[[13,0.03318],[64002,0.00732],[56166,0.00406],[56251,0.00286],[13269,0.00285],[4460,0.0026],[307,0.00253],[56210,0.00205],[285,0.00201],[4961,0.00198]],[[1319,0.01017],[37491,0.00843],[29042,0.00466],[36743,0.0037],[4092,0.00238],[3552,0.00173],[12547,0.00172],[3277,0.00144],[4460,0.00144],[12988,0.00142]]],[[[13,0.07128],[399,0.00508],[797,0.00477],[700,0.00451],[1787,0.00431],[900,0.00393],[1672,0.00369],[64002,0.00334],[56166,0.00297],[285,0.00284]],[[13,0.01034],[4460,0.00193],[4256,0.00178],[56210,0.00177],[1672,0.00175],[3233,0.00165],[57049,0.00148],[19101,0.00145],[2078,0.00137],[1787,0.00125]],[[37491,0.01631],[36743,0.01323],[29042,0.00538],[39584,0.00384],[1319,0.00306],[49300,0.00256],[50541,0.00226],[17198,0.00218],[8251,0.00174],[45408,0.00168]]],[[[13,0.24249],[56166,0.01396],[64002,0.00681],[331,0.00477],[469,0.0038],[56194,0.00373],[56183,0.00342],[16,0.00341],[56191,0.00311],[700,0.0031]],[[13,0.08715],[56166,0.0061],[64002,0.00471],[56191,0.00453],[56210,0.00292],[331,0.00261],[307,0.00253],[469,0.00243],[56183,0.00225],[803,0.00221]],[[13,0.04512],[56166,0.00651],[331,0.00387],[469,0.00265],[64002,0.00182],[803,0.0018],[56191,0.00179],[700,0.00173],[399,0.00169],[341,0.00153]]],[[[13,0.15427],[56195,0.01375],[56166,0.01279],[272,0.00723],[16,0.00635],[262,0.00597],[308,0.00591],[56219,0.00539],[700,0.00483],[471,0.00473]],[[13,0.07149],[56166,0.00644],[56191,0.00452],[64002,0.00311],[56183,0.0027],[803,0.00251],[331,0.00245],[56194,0.00245],[56210,0.0022],[469,0.00216]],[[13,0.02046],[56166,0.00754],[272,0.00451],[262,0.00451],[331,0.0042],[1319,0.00262],[469,0.00224],[700,0.00208],[399,0.0018],[803,0.00165]]],[[[13,0.21416],[56195,0.04629],[308,0.02352],[56219,0.01141],[56166,0.01062],[56193,0.0097],[336,0.00893],[16,0.00868],[272,0.0084],[56220,0.00519]],[[13,0.05688],[56166,0.0047],[56191,0.00336],[56193,0.00285],[331,0.00248],[56183,0.00238],[56194,0.00233],[56220,0.00199],[56219,0.00195],[303,0.00186]],[[13,0.02229],[56166,0.0088],[272,0.008],[331,0.00552],[262,0.0047],[455,0.00376],[471,0.00327],[769,0.00241],[4084,0.00211],[440,0.00196]]],[[[13,0.12509],[56195,0.03194],[301,0.02514],[308,0.02141],[272,0.02113],[336,0.01419],[440,0.01368],[56183,0.0129],[16,0.01201],[56166,0.01083]],[[13,0.1227],[56183,0.05291],[301,0.02595],[56195,0.02419],[56186,0.01932],[303,0.01388],[272,0.01303],[56166,0.01248],[352,0.01047],[308,0.00974]],[[272,0.09514],[262,0.07641],[440,0.01871],[429,0.01618],[56166,0.01438],[301,0.01431],[13,0.01376],[455,0.01122],[407,0.01071],[352,0.00906]]]],"tgt":{"13":{"p":[[3e-06,8e-06,2e-06],[0.004532,0.006389,0.000505],[0.024174,0.03919,0.000628],[0.066619,0.033184,9.7e-05],[0.071277,0.010338,7.1e-05],[0.242493,0.087151,0.045117],[0.154269,0.071487,0.020463],[0.214164,0.056877,0.02229],[0.125087,0.122697,0.013757]],"r":[[40522,24331,43461],[4,3,147],[1,1,121],[1,1,1580],[1,1,2282],[1,1,1],[1,1,1],[1,1,1],[1,1,7]]},"403":{"p":[[0.0,8.1e-05,0.0],[0.001716,0.001773,3.8e-05],[0.002389,0.001043,9.4e-05],[0.002699,0.000187,2.3e-05],[0.000443,1.4e-05,2e-06],[0.000245,8.4e-05,7.5e-05],[0.000881,0.000118,0.000142],[0.001304,0.000157,0.000263],[0.006453,0.003418,0.004231]],"r":[[63439,1993,60458],[17,22,4650],[38,89,1751],[25,674,9165],[186,16947,46007],[357,1722,2220],[85,1089,910],[56,643,375],[19,35,26]]},"956":{"p":[[3e-06,0.0,0.0],[0.000157,4.2e-05,1.9e-05],[0.000381,4e-05,5.6e-05],[0.000317,3e-05,9.4e-05],[0.000409,3.6e-05,6.8e-05],[9e-05,2.1e-05,3.7e-05],[0.000333,2.3e-05,4.3e-05],[0.00072,4.7e-05,9.9e-05],[0.007529,0.000989,0.001614]],"r":[[41365,61937,64105],[930,4384,8687],[371,3655,3158],[384,6321,1672],[205,5989,2393],[1151,9154,5529],[296,8383,4531],[122,3836,1376],[16,91,61]]},"1938":{"p":[[8e-06,4e-06,1.6e-05],[2.1e-05,1.9e-05,9.1e-05],[1.9e-05,8e-06,3.8e-05],[5.6e-05,1.3e-05,2.9e-05],[8.3e-05,9e-06,2.5e-05],[6.7e-05,2e-05,4.3e-05],[0.000155,2.8e-05,7.5e-05],[0.000306,4.8e-05,0.000189],[0.000433,0.000128,0.000246]],"r":[[23856,36361,13885],[8712,9175,1828],[6287,13220,4710],[2445,13668,7368],[1849,23059,8606],[1691,9523,4564],[742,6994,2225],[303,3719,602],[270,710,461]]},"2434":{"p":[[0.000129,1e-06,1.1e-05],[2.4e-05,2.2e-05,8.8e-05],[2.5e-05,1.7e-05,7.2e-05],[2.8e-05,9e-06,2.6e-05],[4e-05,1.6e-05,6.4e-05],[2.2e-05,1.2e-05,2.6e-05],[7.6e-05,1.9e-05,6.4e-05],[6.4e-05,3.3e-05,0.000123],[4.1e-05,9.8e-05,0.000204]],"r":[[1037,53725,18560],[7977,8300,1887],[5002,7720,2388],[4451,17326,8333],[4149,14519,2587],[5749,14538,7862],[1583,10324,2781],[1540,6010,1036],[2097,911,587]]},"6133":{"p":[[2.3e-05,7e-06,0.0],[0.000153,0.000189,1.3e-05],[9.5e-05,0.000136,1e-05],[9.9e-05,0.0001,4e-06],[0.000112,3.2e-05,6e-06],[2.8e-05,2.4e-05,2.2e-05],[5.4e-05,2.9e-05,2.3e-05],[2.8e-05,2.7e-05,2.1e-05],[6.9e-05,3.7e-05,3.3e-05]],"r":[[9397,28679,63846],[948,680,11743],[1536,1075,14242],[1409,1582,32279],[1290,6847,28025],[4486,7926,9658],[2353,6617,8939],[3312,7442,9316],[1406,2278,2908]]},"9103":{"p":[[1.2e-05,5e-06,3e-06],[1e-05,1.9e-05,4e-06],[9e-06,7e-06,5e-06],[2.5e-05,1.5e-05,1.2e-05],[7.7e-05,1.6e-05,2.1e-05],[3e-06,1e-06,2e-06],[2.4e-05,3e-06,6e-06],[2.8e-05,5e-06,2e-05],[2.7e-05,3.6e-05,7.6e-05]],"r":[[17451,33772,40331],[16180,9549,23614],[10549,14182,22672],[5055,11781,16585],[2025,14684,10478],[24283,44995,38510],[5254,37164,24646],[3319,30424,9755],[2869,2303,1424]]},"56166":{"p":[[1e-06,0.000161,5e-06],[0.000592,0.003954,0.00137],[0.012251,0.015664,0.001072],[0.022078,0.004057,0.000122],[0.002967,0.000326,2.4e-05],[0.013964,0.006096,0.006507],[0.012786,0.006439,0.007544],[0.010621,0.004701,0.008802],[0.010829,0.012479,0.014377]],"r":[[50882,643,31883],[118,7,32],[2,2,43],[2,3,1149],[9,138,9001],[2,2,2],[3,2,2],[5,2,2],[10,8,5]]},"56183":{"p":[[2e-06,6e-06,1e-06],[0.001752,0.007379,3.7e-05],[0.00641,0.007675,0.000109],[0.004185,0.00118,4e-06],[0.00091,0.000193,2e-06],[0.003417,0.00225,0.00118],[0.003844,0.002705,0.001134],[0.004612,0.00238,0.00117],[0.012905,0.052913,0.007814]],"r":[[46849,29856,56870],[15,2,4845],[10,4,1436],[13,31,34548],[73,438,51601],[7,9,18],[15,5,22],[13,6,38],[8,2,12]]}}},"67110":{"top":[[[[2518,0.00719],[9966,0.00608],[47725,0.00521],[27309,0.00423],[22194,0.00419],[17563,0.00363],[37163,0.0033],[50668,0.00307],[23442,0.00289],[17673,0.00285]],[[15281,0.00384],[693,0.00372],[40175,0.00343],[8962,0.00333],[26677,0.00296],[20110,0.00254],[2525,0.00231],[19836,0.00224],[53559,0.00219],[39685,0.00216]],[[12891,0.00709],[50259,0.00528],[4511,0.00515],[38226,0.00473],[57074,0.00372],[46756,0.00368],[8763,0.00312],[38785,0.00282],[23852,0.00244],[45343,0.00237]]],[[[6734,0.01648],[3335,0.01495],[6751,0.01469],[1943,0.00929],[1309,0.00867],[1739,0.00735],[364,0.00655],[3902,0.0051],[23580,0.0048],[1530,0.00436]],[[45330,0.00936],[7891,0.00819],[6664,0.00669],[4756,0.00606],[5857,0.00472],[1423,0.00424],[14640,0.00398],[3857,0.00348],[26512,0.00273],[2463,0.00271]],[[1319,0.0688],[37491,0.00889],[24562,0.00711],[376,0.00521],[429,0.00476],[1673,0.00452],[14117,0.00362],[6751,0.0035],[7856,0.00311],[1967,0.00307]]],[[[1228,0.0128],[5329,0.01049],[376,0.00941],[1530,0.00895],[4008,0.00621],[9440,0.00563],[20697,0.00547],[410,0.00501],[6734,0.00481],[271,0.00467]],[[376,0.01577],[505,0.00601],[1967,0.00594],[1030,0.00471],[56669,0.00456],[1406,0.00453],[34233,0.00416],[3100,0.00402],[56889,0.00392],[58108,0.00391]],[[1319,0.08628],[37491,0.03683],[14117,0.01294],[376,0.00535],[1199,0.00514],[494,0.0044],[1673,0.00394],[1967,0.00383],[45408,0.00367],[20697,0.00329]]],[[[1459,0.00974],[1228,0.0081],[376,0.00719],[14556,0.00647],[37491,0.00493],[5464,0.00413],[1530,0.00329],[17438,0.00316],[485,0.00301],[797,0.003]],[[376,0.02379],[2813,0.00967],[56889,0.00616],[1406,0.00476],[797,0.00456],[1228,0.00383],[56314,0.00345],[1322,0.0032],[8902,0.00311],[4460,0.00293]],[[1319,0.03011],[29042,0.02516],[19794,0.01659],[5425,0.01467],[37491,0.01185],[32432,0.01101],[2546,0.01049],[5070,0.00763],[57013,0.00604],[14117,0.0041]]],[[[14556,0.0116],[1459,0.0082],[604,0.00746],[803,0.0047],[5464,0.00439],[1672,0.00433],[3065,0.00407],[285,0.00381],[376,0.00374],[17438,0.00374]],[[13567,0.01394],[2813,0.01197],[376,0.00672],[3233,0.00463],[5464,0.00302],[35870,0.00286],[4460,0.00281],[1672,0.00267],[57757,0.00248],[17234,0.00223]],[[39584,0.05279],[1319,0.03648],[36743,0.02153],[22490,0.01003],[5070,0.00858],[59255,0.00765],[50541,0.00745],[33676,0.00668],[56640,0.00585],[8436,0.00555]]],[[[13,0.01287],[331,0.00395],[56166,0.00356],[56447,0.00343],[1530,0.0028],[803,0.00279],[56210,0.00278],[512,0.00268],[1303,0.00246],[5464,0.00242]],[[13,0.01748],[331,0.00417],[56210,0.0041],[56447,0.0037],[56191,0.00347],[56166,0.00338],[1303,0.00223],[5464,0.00192],[56256,0.00183],[16,0.00166]],[[1319,0.01429],[36743,0.01249],[56352,0.01074],[262,0.00889],[429,0.00708],[797,0.00648],[56447,0.00535],[14181,0.00517],[50541,0.00516],[384,0.00504]]],[[[13,0.00555],[5464,0.00279],[803,0.00268],[56447,0.00266],[331,0.00247],[512,0.00235],[1530,0.00232],[56166,0.00229],[399,0.00184],[1303,0.00179]],[[13,0.00806],[56447,0.00294],[56210,0.00256],[56191,0.00254],[331,0.00253],[56166,0.00219],[5464,0.00207],[723,0.00186],[1303,0.00166],[803,0.00158]],[[1319,0.06334],[39584,0.03011],[262,0.0174],[50541,0.0137],[1585,0.01177],[9275,0.00948],[429,0.0091],[6657,0.00849],[996,0.00748],[1478,0.00746]]],[[[13,0.00559],[1530,0.00266],[5464,0.00252],[512,0.00247],[331,0.00244],[723,0.00237],[1303,0.00217],[803,0.00189],[56166,0.0018],[16,0.00164]],[[13,0.00715],[723,0.00379],[331,0.00244],[5464,0.00206],[1303,0.00189],[56191,0.00176],[56447,0.00171],[1452,0.0017],[56210,0.00157],[42752,0.00153]],[[1319,0.03911],[6009,0.03591],[471,0.03369],[56195,0.02667],[1095,0.02355],[336,0.02226],[10133,0.0177],[667,0.01706],[4084,0.01532],[2280,0.01474]]],[[[956,0.07003],[272,0.01962],[440,0.0124],[262,0.01077],[1095,0.00795],[56195,0.00711],[336,0.00567],[769,0.00521],[840,0.00487],[285,0.0044]],[[56183,0.09261],[56195,0.04196],[56198,0.02191],[301,0.01882],[403,0.01224],[56186,0.01071],[956,0.01015],[336,0.00819],[56208,0.00772],[491,0.00771]],[[1319,0.08059],[281,0.04258],[262,0.03228],[1095,0.03206],[545,0.02911],[817,0.02555],[259,0.02055],[1200,0.01877],[309,0.01846],[754,0.01818]]]],"tgt":{"13":{"p":[[1e-06,1e-06,1e-06],[5.2e-05,0.000271,0.000336],[0.001255,0.003859,0.000591],[0.000485,0.002778,5.5e-05],[0.000258,0.000356,0.000219],[0.012871,0.017484,0.000668],[0.005553,0.008057,0.000486],[0.005593,0.00715,0.004212],[0.001876,0.006375,0.001863]],"r":[[42188,44650,39590],[2969,463,362],[81,12,148],[213,11,2913],[432,222,573],[1,1,186],[1,1,267],[1,1,33],[50,16,75]]},"403":{"p":[[0.0,4.9e-05,0.0],[0.000455,0.000245,2.6e-05],[0.000765,0.000754,1.8e-05],[6.5e-05,0.00016,1e-05],[1.3e-05,1.7e-05,3e-05],[8.4e-05,0.000106,0.000116],[7.5e-05,9.7e-05,8.1e-05],[9.4e-05,0.000131,0.001622],[0.002545,0.01224,0.003904]],"r":[[61886,3963,60343],[280,528,6051],[157,138,7901],[2624,894,12851],[12744,10817,4387],[2149,1560,1249],[2541,1762,1455],[1809,1047,84],[32,5,38]]},"956":{"p":[[0.0,0.0,0.0],[1.8e-05,2.1e-05,9e-06],[5.7e-05,4.9e-05,3.9e-05],[8.9e-05,4.7e-05,0.000149],[5e-05,1.8e-05,0.000382],[2.6e-05,1.6e-05,0.002048],[3.3e-05,1.6e-05,0.005238],[6.9e-05,3e-05,0.001738],[0.070033,0.010148,0.012157]],"r":[[61551,63396,63763],[7387,8107,12941],[2689,3362,4026],[1848,3793,952],[3484,10476,315],[8120,12386,38],[6637,12784,21],[2825,7566,76],[1,7,12]]},"1938":{"p":[[6e-06,4e-06,7e-06],[1.1e-05,5.2e-05,1.3e-05],[2e-06,3e-06,4e-06],[1.1e-05,9e-06,6e-06],[3.2e-05,1.8e-05,4.7e-05],[6.4e-05,4.4e-05,0.00181],[0.0001,6.8e-05,0.002648],[0.000145,9.5e-05,0.000496],[0.001157,0.000412,0.001796]],"r":[[21243,29179,18875],[10511,3428,10172],[23142,26892,20453],[13708,15610,18090],[5609,10337,2945],[3065,4735,52],[1687,2854,38],[954,1794,239],[85,241,79]]},"2434":{"p":[[6e-05,0.0,1e-06],[2.2e-05,9e-06,6e-06],[3e-06,6e-06,9e-06],[1e-06,1e-06,6.4e-05],[1e-06,3e-06,0.00471],[1e-05,1.2e-05,0.002045],[1.2e-05,1.5e-05,0.001146],[1.6e-05,2.2e-05,0.001985],[9.6e-05,0.000369,0.006408]],"r":[[2790,59846,43097],[6326,15680,16703],[19401,17938,12624],[47884,40383,2482],[43837,33960,11],[17025,15038,39],[16395,13793,107],[13383,10328,70],[1499,279,25]]},"6133":{"p":[[2.9e-05,2e-06,0.0],[3.9e-05,2.4e-05,1.6e-05],[5.9e-05,0.000238,3.7e-05],[0.00036,0.000526,1.9e-05],[9.1e-05,8.7e-05,3.6e-05],[8.2e-05,6.5e-05,0.000474],[7.5e-05,5.7e-05,0.000197],[7.5e-05,5.6e-05,0.000671],[0.000137,5.3e-05,0.002913]],"r":[[5875,40494,61193],[3877,7370,9033],[2616,634,4208],[292,161,8174],[1732,1913,3748],[2207,2957,288],[2546,3628,643],[2520,3702,177],[1046,2215,51]]},"9103":{"p":[[1.6e-05,5e-06,4e-06],[6e-06,3.3e-05,3e-06],[2e-06,1.5e-05,6e-06],[2e-05,2.8e-05,2.6e-05],[2.5e-05,1.5e-05,0.000134],[1e-06,1e-06,0.002839],[1e-06,1e-06,0.00089],[2e-06,2e-06,0.000558],[0.000708,0.000384,0.004162]],"r":[[9968,24407,25636],[16264,5348,23094],[23725,9409,16792],[8380,6415,6024],[7085,12701,1026],[46642,50855,25],[43596,48455,140],[39131,45272,212],[164,259,35]]},"56166":{"p":[[1e-06,2.4e-05,3e-06],[0.000982,0.001675,0.000549],[0.002699,0.003052,0.000347],[0.000179,0.000725,2.7e-05],[8.5e-05,8.1e-05,0.000814],[0.003559,0.003384,0.002291],[0.00229,0.002192,0.006524],[0.001801,0.001518,0.004902],[0.003091,0.00405,0.000341]],"r":[[49723,8169,29062],[93,31,182],[24,17,325],[771,93,5839],[1891,2068,115],[3,6,31],[8,6,13],[9,11,28],[20,24,319]]},"56183":{"p":[[1e-06,1e-06,0.0],[0.000104,0.000228,7.1e-05],[0.000413,0.001969,0.000287],[5.4e-05,0.0007,2.8e-05],[1.5e-05,0.000109,0.000109],[0.000608,0.00135,0.000418],[0.000345,0.000902,0.000609],[0.000282,0.00084,0.008091],[0.001154,0.092609,0.001641]],"r":[[39421,46871,52922],[1473,588,2377],[355,32,428],[3257,103,5731],[11242,1423,1269],[92,19,340],[219,30,209],[307,33,16],[88,1,89]]}}},"100660":{"top":[[[[9966,0.01316],[12571,0.01142],[2518,0.01062],[32720,0.00715],[19046,0.0068],[12075,0.00652],[22194,0.00615],[17784,0.00591],[4294,0.00559],[7461,0.00549]],[[26677,0.01068],[23753,0.01043],[693,0.0091],[52339,0.0058],[51504,0.00553],[33394,0.00532],[61893,0.00513],[8962,0.00501],[42944,0.00395],[15460,0.00352]],[[27887,0.00655],[38226,0.0065],[18224,0.00609],[50259,0.0055],[1949,0.00544],[38785,0.00441],[23938,0.00417],[41657,0.00371],[8763,0.00353],[25977,0.00349]]],[[[1739,0.01637],[5412,0.01439],[52706,0.01354],[23580,0.01269],[6734,0.01083],[31451,0.00861],[3661,0.00791],[5216,0.00665],[1530,0.00618],[58042,0.00587]],[[7891,0.02132],[1807,0.01879],[683,0.0131],[14640,0.0077],[39583,0.00664],[56795,0.00609],[19688,0.00571],[38982,0.00498],[56550,0.00496],[25165,0.0042]],[[1319,0.03312],[37491,0.01861],[57013,0.00665],[376,0.00564],[18077,0.00485],[1673,0.00415],[20259,0.00354],[56414,0.00341],[14117,0.00335],[32374,0.00325]]],[[[5329,0.00819],[1673,0.00725],[5538,0.00699],[56989,0.00676],[376,0.00646],[64002,0.00584],[56211,0.00486],[5888,0.0042],[4008,0.00362],[2577,0.00345]],[[1217,0.05851],[5620,0.01071],[25118,0.00838],[56798,0.00832],[57836,0.00816],[56592,0.0061],[1778,0.00572],[45791,0.00563],[5857,0.00491],[21267,0.00433]],[[1319,0.07054],[37491,0.05911],[1217,0.0338],[1673,0.02023],[376,0.01285],[1198,0.00595],[2733,0.00566],[2679,0.00546],[56498,0.00493],[600,0.00461]]],[[[1673,0.01686],[376,0.01134],[2813,0.0071],[34942,0.0059],[5538,0.00539],[1459,0.00533],[14556,0.00406],[3187,0.00316],[58108,0.00315],[56308,0.00302]],[[56883,0.04073],[56475,0.02783],[56758,0.01914],[56368,0.01082],[6884,0.0097],[6862,0.0091],[26976,0.00863],[12932,0.00853],[56710,0.00763],[11445,0.00676]],[[32432,0.09621],[19744,0.02894],[19794,0.02835],[37491,0.01747],[29042,0.01541],[5425,0.00967],[57013,0.0081],[2806,0.00622],[2149,0.00565],[22490,0.00562]]],[[[3233,0.0199],[1673,0.00561],[34942,0.00551],[3187,0.00458],[3417,0.00457],[2813,0.00453],[376,0.00438],[1459,0.00391],[14556,0.00362],[19101,0.00317]],[[56475,0.13876],[56183,0.11161],[879,0.02438],[307,0.01252],[56174,0.00961],[376,0.00827],[689,0.00701],[412,0.00683],[56186,0.00658],[4260,0.00643]],[[13002,0.05013],[2147,0.04674],[22490,0.03632],[57933,0.01781],[27903,0.00971],[56232,0.00948],[9001,0.00841],[36743,0.00811],[4987,0.00706],[56385,0.00699]]],[[[56447,0.00835],[13,0.00759],[331,0.00356],[1303,0.00325],[5464,0.00324],[56166,0.00264],[56698,0.00249],[16,0.00219],[749,0.00197],[56210,0.0019]],[[56183,0.18418],[56186,0.04468],[403,0.03602],[280,0.02464],[13,0.02246],[307,0.02194],[56191,0.01968],[301,0.01766],[56166,0.01558],[56475,0.01381]],[[442,0.03051],[22490,0.02427],[311,0.01239],[36743,0.01203],[320,0.01103],[337,0.01066],[420,0.0093],[56231,0.00809],[56166,0.00781],[57110,0.00696]]],[[[56447,0.00652],[13,0.00408],[5464,0.00314],[1303,0.00311],[331,0.0022],[56698,0.00197],[56166,0.00169],[749,0.00163],[52895,0.00156],[16,0.00146]],[[56191,0.11038],[56183,0.05785],[56174,0.03471],[56195,0.02958],[879,0.02742],[13,0.02397],[307,0.01716],[260,0.01363],[56166,0.0132],[403,0.01246]],[[56166,0.16811],[50541,0.03328],[1194,0.02421],[1319,0.02276],[262,0.01872],[39584,0.01789],[3201,0.01377],[336,0.01331],[545,0.01207],[360,0.00917]]],[[[56447,0.00482],[13,0.0036],[1303,0.00343],[5464,0.00272],[331,0.00216],[723,0.00173],[52895,0.00165],[56166,0.00141],[56698,0.0014],[56524,0.00134]],[[56183,0.14219],[56195,0.10629],[56191,0.07148],[56186,0.04613],[13,0.04199],[56198,0.0405],[403,0.03842],[2196,0.0191],[14294,0.01545],[56174,0.01498]],[[56166,0.14805],[2434,0.12282],[336,0.05427],[13,0.05182],[738,0.04634],[293,0.03103],[2280,0.01916],[324,0.01488],[262,0.01478],[1319,0.01436]]],[[[56166,0.04378],[272,0.01887],[336,0.01791],[262,0.01768],[301,0.01752],[56195,0.01189],[13,0.00995],[352,0.00884],[956,0.00727],[632,0.00674]],[[56183,0.15094],[403,0.12268],[13,0.1007],[56195,0.08438],[308,0.05929],[56186,0.03161],[56208,0.03119],[301,0.01778],[56198,0.01681],[56191,0.01586]],[[2434,0.19107],[9103,0.11092],[13,0.04834],[309,0.033],[293,0.03037],[259,0.0301],[487,0.02751],[262,0.01778],[288,0.015],[56166,0.01471]]]],"tgt":{"13":{"p":[[1e-06,0.0,1e-06],[2.9e-05,2.2e-05,0.000177],[0.002182,3.9e-05,0.000109],[0.000679,0.000685,7.5e-05],[0.000405,0.002229,0.000116],[0.007593,0.022457,0.001467],[0.004078,0.023967,0.003978],[0.003604,0.041987,0.051815],[0.00995,0.100698,0.048339]],"r":[[39746,49688,38631],[4735,6576,863],[31,3880,1236],[123,158,1750],[218,33,1070],[2,5,58],[2,6,26],[2,5,4],[7,3,3]]},"403":{"p":[[0.0,2.3e-05,0.0],[0.000425,6.1e-05,1.4e-05],[0.000171,4.8e-05,2e-06],[1.5e-05,0.000125,2e-06],[6e-06,0.006306,8e-06],[5.6e-05,0.036021,5.6e-05],[4.3e-05,0.012459,0.00011],[4.2e-05,0.03842,0.002833],[0.003075,0.122677,0.006981]],"r":[[58622,6773,59284],[288,2663,9985],[955,3161,24548],[10599,1089,30215],[20542,11,11490],[3802,3,2506],[5162,10,824],[5501,7,44],[28,2,22]]},"956":{"p":[[0.0,0.0,0.0],[5e-06,1.1e-05,7e-06],[5e-06,2.4e-05,9e-06],[5e-06,4.8e-05,0.00017],[2e-06,2.8e-05,4.5e-05],[7e-06,0.00012,6e-05],[7e-06,0.00045,0.000472],[8e-06,0.000851,0.001876],[0.007272,0.013569,0.001394]],"r":[[60963,60771,61707],[16045,11362,15799],[18405,5859,11720],[22540,2677,671],[33432,3364,2883],[21088,691,2333],[22331,207,223],[20579,79,57],[9,11,79]]},"1938":{"p":[[8e-06,3e-06,4e-06],[4e-06,1e-05,1e-06],[2e-06,1e-06,1e-06],[8e-06,8e-06,1e-06],[1.3e-05,4e-06,4.6e-05],[7.7e-05,2e-05,0.000757],[9.2e-05,3e-06,0.000493],[0.000101,2e-06,0.000432],[0.000893,1.6e-05,0.00593]],"r":[[13813,26323,23013],[17964,12222,34659],[28146,34869,38645],[16623,11062,36116],[12616,13324,2783],[2525,3228,159],[2006,13777,213],[1748,15591,178],[128,1660,29]]},"2434":{"p":[[4.8e-05,0.0,1e-06],[2e-05,1e-06,3e-06],[2e-06,5e-06,3e-06],[0.0,4.4e-05,6.1e-05],[1e-06,2.2e-05,0.002214],[1.2e-05,1.3e-05,0.001127],[1.2e-05,2e-06,0.000537],[1.3e-05,3.7e-05,0.122824],[0.000122,0.000107,0.191072]],"r":[[3120,61650,38748],[6492,35665,24189],[27958,18392,22430],[52814,2834,2174],[50385,4069,37],[15064,4467,92],[15709,18531,189],[15287,1608,2],[1041,383,1]]},"6133":{"p":[[3.7e-05,0.0,0.0],[0.000122,2.6e-05,1.9e-05],[0.000117,0.000516,3.8e-05],[0.000309,0.000676,1e-05],[0.000141,0.000499,7e-06],[7.2e-05,0.000625,7.9e-05],[6.2e-05,0.000202,0.000318],[5.8e-05,9.4e-05,0.000809],[7.4e-05,0.000204,0.011006]],"r":[[4029,50301,54906],[1197,5871,7767],[1462,214,3626],[354,160,10630],[997,185,13081],[2758,156,1793],[3346,440,334],[3704,667,115],[1668,238,16]]},"9103":{"p":[[1.1e-05,4e-06,1.2e-05],[1e-06,1.5e-05,4e-06],[1e-06,3.4e-05,7e-06],[3e-06,0.000111,5.7e-05],[3e-06,4.9e-05,8.5e-05],[0.0,1.2e-05,0.00037],[0.0,5e-06,0.000371],[1e-06,0.000313,0.014146],[0.000421,0.001929,0.110923]],"r":[[10519,22682,11192],[34413,9112,21405],[36806,4374,13078],[29553,1237,2308],[29253,2082,1531],[54040,4647,335],[54278,10049,293],[53290,212,12],[280,41,2]]},"56166":{"p":[[1e-06,8e-06,3e-06],[0.00087,0.000128,0.000467],[0.001732,0.000115,0.000254],[0.000172,0.001195,4.4e-05],[7.1e-05,0.001436,0.000182],[0.002636,0.01558,0.007807],[0.00169,0.0132,0.168113],[0.001409,0.004074,0.148049],[0.043783,0.009836,0.014707]],"r":[[38682,15336,25292],[123,1226,241],[44,1282,439],[801,89,3038],[2389,55,656],[6,9,9],[7,9,1],[8,19,1],[1,14,10]]},"56183":{"p":[[1e-06,0.0,0.0],[9.5e-05,8.2e-05,6.8e-05],[0.000347,0.000375,9.7e-05],[5.8e-05,0.004711,1.2e-05],[2.4e-05,0.111606,4.1e-05],[0.000403,0.184178,0.000301],[0.00026,0.057845,0.000672],[0.000214,0.142188,0.002903],[0.005276,0.150938,0.000456]],"r":[[32816,50145,49912],[1542,1976,2580],[407,326,1392],[3070,19,9066],[7436,2,3094],[175,1,433],[355,2,159],[493,1,42],[16,1,169]]}}},"201330":{"top":[[[[49715,0.03537],[12571,0.02967],[26518,0.02609],[54301,0.0243],[12075,0.019],[17784,0.01814],[13846,0.01767],[19046,0.01659],[8153,0.01416],[16321,0.01177]],[[16752,0.08143],[16352,0.05335],[51835,0.04952],[52826,0.04799],[13577,0.02832],[1517,0.01308],[12437,0.0124],[20900,0.01181],[60087,0.011],[50011,0.0107]],[[14992,0.01523],[38785,0.01424],[48258,0.0139],[31674,0.01295],[1949,0.0128],[23657,0.00977],[26885,0.00852],[21193,0.00831],[36866,0.00781],[48951,0.00726]]],[[[52706,0.02458],[5457,0.01173],[6734,0.00974],[34418,0.00713],[27958,0.00699],[494,0.0068],[767,0.00677],[13666,0.00645],[34124,0.00619],[5216,0.00617]],[[33492,0.01752],[14640,0.01667],[39583,0.01098],[53595,0.0103],[15731,0.01008],[29548,0.00664],[46255,0.00619],[11366,0.00583],[57806,0.00571],[13577,0.00534]],[[57013,0.02678],[1319,0.01921],[56656,0.00611],[56418,0.00497],[1967,0.00495],[27958,0.00438],[11869,0.0041],[54219,0.00404],[58650,0.00403],[13026,0.00402]]],[[[56989,0.01498],[1673,0.01282],[376,0.01183],[64002,0.00731],[56669,0.00724],[56591,0.00485],[5538,0.00436],[5329,0.00396],[56764,0.00374],[15032,0.00363]],[[56798,0.01548],[19652,0.01057],[3831,0.01036],[53595,0.01003],[1217,0.00981],[30237,0.00853],[1778,0.0078],[16369,0.00777],[12230,0.00487],[3830,0.00477]],[[17139,0.04792],[1217,0.02968],[1319,0.02453],[2733,0.0206],[21259,0.0195],[2469,0.01407],[2679,0.01311],[12625,0.0103],[18900,0.00994],[1394,0.00893]]],[[[1673,0.0546],[376,0.02057],[3857,0.00738],[16012,0.00662],[56669,0.00658],[2813,0.005],[5538,0.00407],[57531,0.00364],[6534,0.00319],[9681,0.0028]],[[56710,0.07863],[56475,0.07156],[56798,0.01877],[2712,0.01287],[14640,0.0087],[53595,0.00815],[877,0.00699],[3831,0.00554],[56183,0.00484],[403,0.00463]],[[392,0.03831],[2612,0.02613],[18900,0.02199],[32443,0.01684],[3536,0.01586],[614,0.01547],[56521,0.01352],[57013,0.01349],[30300,0.01271],[56498,0.0125]]],[[[3857,0.01517],[1673,0.01142],[14950,0.00706],[32432,0.00668],[5464,0.00588],[15812,0.00568],[56850,0.00491],[13567,0.00485],[4460,0.00461],[376,0.00416]],[[56475,0.11199],[56183,0.04244],[298,0.03823],[56957,0.03608],[403,0.02511],[1720,0.0212],[57392,0.02011],[1194,0.01076],[280,0.0103],[307,0.0103]],[[2147,0.05907],[4987,0.03148],[1967,0.02665],[1309,0.02002],[18108,0.01877],[9001,0.01877],[3536,0.01791],[56423,0.01616],[5329,0.00996],[13002,0.00858]]],[[[56447,0.00768],[5464,0.00453],[723,0.00437],[530,0.00298],[56608,0.0027],[4241,0.00266],[19684,0.00185],[19573,0.00179],[13,0.00171],[16,0.00165]],[[56183,0.10525],[403,0.10081],[301,0.04511],[56475,0.04196],[13,0.03971],[56166,0.02566],[956,0.02404],[307,0.02298],[1720,0.02101],[404,0.01985]],[[442,0.03953],[1967,0.02172],[311,0.02068],[56377,0.01948],[430,0.0143],[661,0.01353],[2890,0.00901],[1523,0.00864],[20612,0.00831],[24211,0.0075]]],[[[56447,0.00521],[723,0.00471],[5464,0.00387],[530,0.00352],[56608,0.00263],[4241,0.00241],[19573,0.00222],[19684,0.00176],[1600,0.00176],[45372,0.00162]],[[56183,0.0339],[956,0.0308],[56475,0.0285],[56195,0.02381],[56191,0.01756],[403,0.01199],[879,0.01162],[6281,0.01142],[56166,0.01124],[56198,0.01099]],[[6664,0.07039],[1184,0.05646],[1687,0.04585],[3831,0.03803],[752,0.02657],[2315,0.0157],[16346,0.01418],[57523,0.0133],[632,0.01058],[59041,0.01012]]],[[[723,0.005],[530,0.00398],[56447,0.00381],[5464,0.0031],[56608,0.00267],[19573,0.00236],[1600,0.00194],[4241,0.00189],[36549,0.0017],[45372,0.00165]],[[56183,0.06941],[56195,0.06901],[403,0.0354],[56198,0.02244],[376,0.02235],[2196,0.01556],[56191,0.01321],[956,0.01065],[56186,0.00905],[13,0.00739]],[[4628,0.08745],[2196,0.03634],[5462,0.0284],[2082,0.02678],[2434,0.01528],[632,0.01493],[1309,0.01485],[738,0.01349],[808,0.0133],[466,0.01273]]],[[[262,0.02878],[56166,0.01382],[272,0.01293],[402,0.01065],[632,0.01002],[403,0.00948],[956,0.00852],[301,0.00779],[297,0.0074],[569,0.00629]],[[56183,0.48721],[403,0.18681],[13,0.0544],[956,0.03053],[56195,0.02959],[2082,0.01484],[56208,0.01093],[56186,0.01074],[56198,0.01015],[56166,0.00672]],[[2434,0.65047],[6133,0.02158],[309,0.01755],[262,0.01398],[8436,0.01261],[342,0.01003],[6934,0.00976],[7088,0.00895],[738,0.00886],[18907,0.00837]]]],"tgt":{"13":{"p":[[0.0,0.0,0.0],[3.9e-05,5e-06,8.4e-05],[0.000979,0.000103,5e-06],[0.0002,0.00205,1.7e-05],[0.000234,0.004688,3e-05],[0.001708,0.03971,0.001271],[0.000932,0.006676,0.00066],[0.000777,0.007389,0.000518],[0.001365,0.0544,0.000148]],"r":[[35727,43481,40879],[3511,14885,2017],[90,1485,13949],[670,49,5525],[568,21,3645],[9,5,99],[37,18,173],[57,10,227],[95,3,231]]},"403":{"p":[[0.0,1.2e-05,0.0],[0.000158,3.8e-05,1e-05],[0.000166,0.000854,1e-06],[1.5e-05,0.00463,1e-06],[8e-06,0.025109,1.1e-05],[3.3e-05,0.100811,0.000586],[2.4e-05,0.011991,5.3e-05],[2.3e-05,0.035399,0.000134],[0.009479,0.186806,0.000681]],"r":[[51323,6527,60231],[961,3646,11623],[1043,121,28369],[9705,10,32329],[15370,5,7557],[6366,2,227],[8620,6,1775],[9197,3,687],[6,2,78]]},"956":{"p":[[0.0,0.0,0.0],[1e-06,1e-05,3e-06],[2e-06,4e-05,1.3e-05],[4e-06,0.000381,0.000192],[3e-06,0.001985,0.000226],[1.7e-05,0.024039,0.000813],[1.6e-05,0.030799,0.007509],[1.5e-05,0.010651,0.000436],[0.008519,0.030527,0.00094]],"r":[[62040,53582,53302],[25422,9843,23841],[28198,3843,7717],[23286,331,605],[26862,47,568],[11729,7,168],[12421,2,13],[13245,8,273],[7,4,64]]},"1938":{"p":[[1.6e-05,2e-06,1e-06],[1.1e-05,1e-06,0.0],[2e-06,0.0,0.0],[4e-06,1e-06,0.0],[8e-06,1e-06,1e-05],[0.00014,3e-06,5.8e-05],[0.000142,9e-06,0.000469],[0.000142,1e-06,0.003439],[0.001552,2e-06,0.004079]],"r":[[5546,18440,29542],[8675,37430,44384],[27431,51667,59206],[22448,23454,61449],[14752,26586,8306],[1112,8326,2076],[1073,8073,249],[1041,21240,41],[76,3566,19]]},"2434":{"p":[[2.3e-05,0.0,0.0],[2e-05,1e-06,1e-06],[3e-06,3e-06,1e-06],[1e-06,6.6e-05,1e-06],[1e-06,0.000331,0.000238],[8e-06,3.3e-05,3.9e-05],[7e-06,3.2e-05,1.9e-05],[8e-06,0.00081,0.015279],[0.000132,0.000903,0.650466]],"r":[[4296,61782,46832],[5778,32962,33033],[22087,22053,32582],[37098,1852,23002],[40764,358,542],[19504,1720,2876],[20798,3261,3810],[20011,149,5],[1100,40,1]]},"6133":{"p":[[2.3e-05,0.0,0.0],[0.000473,2.9e-05,2.7e-05],[3.3e-05,3.4e-05,1.7e-05],[5.9e-05,7.1e-05,1.1e-05],[1.9e-05,0.000187,8.9e-05],[1e-05,0.000857,6.5e-05],[8e-06,3.7e-05,9.5e-05],[8e-06,2.1e-05,0.001237],[9.5e-05,3.8e-05,0.02158]],"r":[[4281,53047,42514],[297,4590,5645],[4873,4379,6274],[2850,1733,7653],[8125,593,1429],[16625,99,1872],[19697,2906,1109],[20004,4004,107],[1537,424,2]]},"9103":{"p":[[1.4e-05,0.0,7e-06],[3e-06,5e-06,1.9e-05],[3e-06,2e-06,5e-06],[6e-06,2.6e-05,3e-06],[6e-06,5.8e-05,1.7e-05],[1e-06,4.2e-05,5.8e-05],[1e-06,2.9e-05,1.6e-05],[2e-06,0.000551,0.000217],[0.001098,0.000519,0.003977]],"r":[[6051,39351,11485],[18025,15548,7706],[23973,28246,15038],[17599,3946,16088],[18188,1640,5556],[42124,1420,2084],[41157,3506,4243],[38701,211,451],[120,62,21]]},"56166":{"p":[[0.0,7e-06,3e-06],[0.000985,8.6e-05,0.00036],[0.000896,9.3e-05,8.6e-05],[8.4e-05,0.002515,7e-05],[3.9e-05,0.002571,0.00032],[0.000913,0.025663,0.004655],[0.00058,0.011241,0.0059],[0.000475,0.002064,0.008712],[0.013818,0.006724,0.001554]],"r":[[36952,8894,20252],[120,1761,353],[104,1680,1458],[1924,33,1629],[4502,33,391],[43,6,17],[100,9,15],[146,49,17],[2,10,38]]},"56183":{"p":[[2e-06,1e-06,0.0],[0.000133,3.6e-05,4.4e-05],[0.000308,0.000207,4.7e-05],[6.3e-05,0.004836,9e-06],[3.5e-05,0.042436,1.8e-05],[0.000179,0.105252,0.000146],[0.000117,0.033903,4.6e-05],[0.0001,0.069406,3e-05],[0.000929,0.487208,2.9e-05]],"r":[[18894,28782,52446],[1155,3854,3784],[479,702,2702],[2675,9,8311],[4941,2,5352],[756,1,931],[1444,1,1979],[1754,1,2286],[140,1,681]]}}},"402650":{"top":[[[[13846,0.07245],[54301,0.04063],[30954,0.02831],[10721,0.01983],[16321,0.01496],[28940,0.01442],[26518,0.01047],[12571,0.00962],[16112,0.0091],[17784,0.00721]],[[22928,0.27559],[53772,0.18079],[16752,0.03445],[16352,0.01741],[50058,0.01495],[8962,0.00811],[57552,0.00741],[37680,0.00687],[16081,0.00667],[60087,0.00642]],[[22016,0.42889],[54342,0.06999],[53697,0.0203],[48951,0.01582],[63353,0.01051],[20773,0.01029],[10913,0.00882],[53250,0.00759],[1949,0.00758],[5714,0.00681]]],[[[767,0.04236],[13846,0.01655],[5627,0.01504],[27958,0.01009],[629,0.00742],[15862,0.00729],[287,0.00675],[10147,0.00624],[13002,0.00594],[1775,0.00498]],[[44246,0.38453],[52498,0.03821],[10023,0.03282],[14640,0.01814],[41856,0.01424],[56798,0.0112],[17935,0.00789],[40114,0.00726],[56389,0.00664],[3273,0.0058]],[[47862,0.01497],[1319,0.01407],[57013,0.00967],[27958,0.00964],[23210,0.00608],[57394,0.00566],[7027,0.00429],[33137,0.00362],[56731,0.0036],[21940,0.0034]]],[[[56591,0.00687],[56308,0.00544],[2813,0.00538],[56989,0.00521],[10434,0.0048],[15032,0.00471],[12234,0.00403],[3264,0.00396],[376,0.00351],[18320,0.00317]],[[3831,0.06825],[1217,0.02872],[6917,0.02544],[6233,0.01743],[57312,0.0116],[11609,0.01158],[30237,0.00877],[3280,0.00834],[42926,0.00767],[6633,0.00763]],[[29235,0.0271],[32330,0.02385],[44782,0.01602],[735,0.01578],[2733,0.0138],[5070,0.0102],[2200,0.00878],[4649,0.00744],[17139,0.00694],[28594,0.0069]]],[[[1673,0.01103],[56556,0.00576],[376,0.00522],[2813,0.00518],[2270,0.00501],[610,0.0041],[3264,0.00397],[478,0.00346],[56308,0.00329],[36073,0.00323]],[[56475,0.197],[3280,0.01615],[56423,0.01405],[1194,0.00974],[25189,0.00822],[6633,0.00809],[56591,0.00789],[56174,0.00776],[56798,0.00744],[52791,0.00733]],[[29235,0.07689],[5070,0.05224],[14695,0.01464],[1197,0.01186],[8227,0.01169],[771,0.00871],[13692,0.00827],[3279,0.0077],[6895,0.00745],[32443,0.00741]]],[[[2270,0.01596],[1673,0.00569],[478,0.00556],[39975,0.00469],[3857,0.00467],[610,0.00451],[578,0.00448],[4460,0.00371],[36073,0.00355],[19684,0.0032]],[[56475,0.23391],[52791,0.05064],[56351,0.0329],[56171,0.01735],[412,0.01489],[298,0.0143],[56591,0.01125],[307,0.01117],[3581,0.00982],[2971,0.00851]],[[4987,0.04109],[735,0.02682],[1933,0.02562],[5277,0.02468],[56907,0.02367],[9001,0.01681],[2434,0.01602],[1714,0.00939],[932,0.00721],[59384,0.0072]]],[[[530,0.01507],[21845,0.00844],[56447,0.00546],[14957,0.00463],[478,0.00429],[19684,0.00311],[5464,0.00264],[723,0.00263],[10366,0.00249],[6576,0.0024]],[[56475,0.14406],[307,0.09803],[301,0.04142],[403,0.04101],[56244,0.03139],[56183,0.03031],[56186,0.01957],[404,0.01729],[956,0.01519],[56260,0.01339]],[[311,0.03462],[442,0.02866],[5329,0.01865],[60312,0.01767],[661,0.01652],[17849,0.01368],[1933,0.01341],[5598,0.01233],[18095,0.01209],[293,0.01149]]],[[[530,0.01487],[21845,0.01025],[14957,0.00503],[478,0.00498],[56447,0.0038],[19684,0.00274],[6576,0.00268],[10366,0.00264],[723,0.00262],[2819,0.00238]],[[56475,0.0996],[56191,0.03498],[956,0.03402],[52791,0.01371],[320,0.01055],[56166,0.01039],[403,0.00954],[307,0.00895],[301,0.00888],[295,0.00879]],[[263,0.10415],[293,0.06042],[555,0.03242],[1714,0.01886],[260,0.01701],[56166,0.01669],[334,0.01613],[336,0.0145],[8608,0.01299],[467,0.01251]]],[[[530,0.01605],[21845,0.01446],[478,0.00492],[14957,0.00457],[6576,0.00294],[56447,0.00277],[723,0.00272],[10366,0.00271],[578,0.00226],[19684,0.00223]],[[52791,0.03565],[19470,0.03512],[2082,0.02678],[1915,0.02492],[403,0.01998],[13846,0.01696],[56198,0.01659],[56183,0.01597],[56191,0.01588],[56220,0.01488]],[[336,0.17836],[2434,0.15924],[56220,0.07343],[808,0.04984],[466,0.03256],[1714,0.02186],[376,0.01902],[293,0.01401],[4628,0.01209],[19345,0.01117]]],[[[58259,0.86933],[956,0.00389],[23939,0.00169],[29706,0.0007],[58727,0.00055],[23479,0.00055],[1938,0.00052],[17511,0.00051],[59787,0.00041],[9103,0.0004]],[[403,0.42437],[56183,0.20128],[13,0.06004],[2082,0.03786],[56186,0.02825],[9103,0.01654],[56166,0.01572],[19470,0.0129],[956,0.01062],[2434,0.00745]],[[2434,0.93541],[336,0.00901],[9103,0.00888],[19345,0.00574],[56166,0.00238],[893,0.00237],[309,0.00211],[8436,0.00172],[7727,0.00149],[12057,0.0011]]]],"tgt":{"13":{"p":[[1e-06,0.0,0.0],[1.4e-05,7e-06,3.9e-05],[0.000333,7.5e-05,2e-05],[7.7e-05,0.001524,0.000353],[8.7e-05,0.004465,0.000211],[0.000251,0.013342,0.002887],[0.000144,0.007318,0.003419],[0.000124,0.004473,0.000157],[3.2e-05,0.060037,9.6e-05]],"r":[[20305,43480,39179],[7910,6950,4131],[396,1809,5143],[2286,56,408],[1923,24,617],[544,11,51],[1106,13,40],[1279,25,398],[633,3,72]]},"403":{"p":[[0.0,3e-06,0.0],[8.3e-05,4.3e-05,1e-05],[0.000122,0.000262,1e-06],[1.8e-05,0.004443,2e-06],[1.1e-05,0.004427,0.000165],[1.6e-05,0.041011,0.000541],[1.2e-05,0.009538,0.00109],[1.1e-05,0.019983,0.000188],[9.2e-05,0.424369,0.000199]],"r":[[46428,9693,60656],[1844,1662,11849],[1430,490,31630],[9045,17,18105],[12476,25,784],[10603,4,258],[13437,7,125],[14035,5,349],[137,1,35]]},"956":{"p":[[0.0,0.0,0.0],[1e-06,1.3e-05,5e-06],[7e-06,4.1e-05,1.3e-05],[3e-06,0.000742,0.000299],[4e-06,0.001216,6.9e-05],[9e-06,0.015188,0.000643],[8e-06,0.034018,0.001617],[7e-06,0.011244,0.00166],[0.003894,0.010619,0.000167]],"r":[[63607,51508,50366],[35130,4171,18250],[15793,3131,7127],[25064,147,480],[21458,70,1623],[16371,9,230],[17603,3,89],[18691,14,49],[2,9,39]]},"1938":{"p":[[3.6e-05,3e-06,0.0],[3.5e-05,0.0,0.0],[4e-06,1e-06,0.0],[3e-06,2e-06,0.0],[2e-06,2e-06,0.0],[2.4e-05,7e-06,3e-06],[2.5e-05,3.8e-05,5.2e-05],[2.2e-05,1.5e-05,0.000161],[0.000522,0.000125,5.8e-05]],"r":[[2738,9880,26651],[3950,31201,47137],[22728,31248,53396],[26920,18468,63088],[31941,14142,51332],[7594,5230,10695],[7383,2576,1459],[8083,5102,387],[7,202,97]]},"2434":{"p":[[6.9e-05,0.0,0.0],[8.1e-05,0.0,1e-06],[6e-06,8e-06,9e-06],[3e-06,7.4e-05,2.3e-05],[2e-06,0.000238,0.016021],[8e-06,5.9e-05,0.002601],[7e-06,4.3e-05,0.00153],[8e-06,0.001038,0.159237],[2.3e-05,0.007453,0.93541]],"r":[[1639,40207,51309],[1876,33072,39613],[16958,10970,9502],[25770,1503,4088],[29748,382,7],[18043,1221,57],[18477,2364,96],[17238,110,2],[972,10,1]]},"6133":{"p":[[3e-06,0.0,0.0],[0.000108,9e-06,5e-06],[1e-05,2.7e-05,3e-06],[1e-05,3.5e-05,0.0],[6e-06,0.000222,1e-06],[4e-06,0.000356,7e-06],[3e-06,0.000127,1e-05],[4e-06,0.000184,0.000265],[3.3e-05,0.000442,0.000618]],"r":[[12446,25373,52579],[1403,5750,18120],[12861,4460,17359],[13965,2894,46619],[17871,413,24887],[25322,262,6837],[27570,950,4634],[27273,597,273],[605,82,17]]},"9103":{"p":[[9.6e-05,1e-06,1e-06],[0.000109,0.0,2.2e-05],[2.4e-05,4.1e-05,2.9e-05],[7.1e-05,0.000237,1e-06],[3.8e-05,0.000649,6e-06],[2.5e-05,0.00015,6.5e-05],[3e-05,0.000189,8.3e-05],[3.6e-05,0.002128,0.002577],[0.000401,0.016539,0.008884]],"r":[[1228,17093,22646],[1396,29482,6829],[6915,3155,3868],[2478,517,24674],[4476,136,8508],[7423,548,1534],[6095,664,1015],[5191,45,32],[10,6,3]]},"56166":{"p":[[1e-06,3e-06,1e-06],[0.000459,8.6e-05,0.000353],[0.00026,3.6e-05,8.6e-05],[3.4e-05,0.00089,0.000692],[1.9e-05,0.003987,0.000506],[0.000172,0.008406,0.002785],[0.000106,0.010387,0.01669],[8.5e-05,0.001827,0.004639],[0.000142,0.015716,0.002377]],"r":[[23478,9651,22052],[308,884,374],[554,3558,1489],[5182,119,181],[8213,27,269],[886,14,53],[1555,6,6],[1996,55,17],[69,7,5]]},"56183":{"p":[[6e-06,2e-06,0.0],[0.000217,4.4e-05,1.7e-05],[0.000161,0.000159,5e-06],[4.1e-05,0.003415,3.9e-05],[3.3e-05,0.007937,4.4e-05],[5.3e-05,0.03031,0.000576],[3.7e-05,0.007784,0.00059],[3.2e-05,0.015973,1.3e-05],[0.000128,0.201276,1.5e-05]],"r":[[8617,13617,57117],[706,1639,8036],[1009,837,13155],[4277,26,2791],[5187,13,2309],[3553,6,248],[4999,12,195],[5849,8,2576],[77,2,265]]}}},"704640":{"top":[[[[29427,0.06051],[57062,0.03233],[375,0.02566],[27133,0.0184],[8153,0.0138],[47554,0.01341],[54508,0.01216],[10721,0.00956],[6005,0.00846],[14122,0.00787]],[[16752,0.28388],[42411,0.02928],[33195,0.02041],[50744,0.01857],[46292,0.01329],[11088,0.01143],[60397,0.0098],[28581,0.00955],[39931,0.00936],[55461,0.00888]],[[20773,0.12878],[53697,0.09849],[54342,0.07639],[22016,0.07523],[5200,0.01956],[13648,0.01557],[30250,0.0098],[48951,0.0096],[10913,0.00883],[59405,0.00882]]],[[[767,0.04342],[10147,0.01785],[56254,0.01109],[629,0.01072],[27958,0.00959],[8312,0.00836],[56251,0.00743],[3500,0.00691],[57011,0.00641],[39250,0.00641]],[[52498,0.28947],[44246,0.15811],[14640,0.10167],[41856,0.01307],[57972,0.01095],[57678,0.01029],[9951,0.00944],[56389,0.00635],[50100,0.0057],[8328,0.00545]],[[47862,0.09995],[27958,0.06393],[1319,0.04552],[5390,0.01515],[19688,0.00839],[28594,0.00613],[46795,0.00526],[23210,0.00488],[8201,0.00485],[56325,0.00426]]],[[[670,0.01095],[1829,0.00859],[56519,0.00714],[56254,0.00713],[56308,0.00552],[56323,0.00511],[56412,0.00501],[44474,0.00475],[56433,0.00469],[16442,0.00398]],[[6917,0.12014],[7386,0.02155],[3831,0.0184],[42926,0.01538],[57312,0.01423],[57813,0.01181],[11609,0.00862],[48870,0.00855],[51816,0.00694],[56349,0.00606]],[[32330,0.12196],[31018,0.05488],[35271,0.04141],[27134,0.02197],[33978,0.01276],[39950,0.01237],[14908,0.01189],[44782,0.01119],[735,0.01054],[55559,0.01012]]],[[[2270,0.06096],[610,0.01639],[478,0.01418],[1801,0.01005],[43811,0.00913],[1625,0.0089],[604,0.00669],[24858,0.00635],[767,0.00584],[7764,0.00537]],[[56798,0.02174],[56475,0.02034],[1194,0.01168],[879,0.01072],[2927,0.00983],[5535,0.00883],[52791,0.0087],[56174,0.00763],[6204,0.00725],[11636,0.00717]],[[24633,0.08806],[10998,0.04752],[6895,0.03502],[57701,0.03295],[29235,0.02883],[5053,0.02214],[870,0.01497],[12899,0.01188],[34132,0.01067],[1009,0.01063]]],[[[2270,0.26148],[24858,0.00883],[610,0.00755],[478,0.00676],[1625,0.00646],[767,0.00639],[11869,0.00585],[264,0.00479],[578,0.00457],[56433,0.00391]],[[56475,0.24727],[52791,0.02427],[56171,0.02419],[57312,0.01825],[307,0.01142],[1568,0.0114],[647,0.01086],[56423,0.01034],[1923,0.01008],[56195,0.00747]],[[5124,0.08162],[1504,0.03735],[47917,0.02764],[32835,0.02761],[38464,0.0274],[16746,0.01832],[4987,0.01731],[57918,0.01375],[2285,0.01085],[56907,0.01079]]],[[[530,0.02207],[61236,0.00946],[2270,0.00879],[478,0.00703],[21845,0.00597],[15725,0.00379],[2002,0.00318],[42978,0.00316],[42814,0.00304],[723,0.00283]],[[56186,0.0806],[307,0.06581],[56472,0.04973],[56183,0.04556],[403,0.03018],[404,0.0245],[56475,0.02429],[2161,0.01988],[30093,0.01779],[13,0.0168]],[[1967,0.04604],[18095,0.03678],[57792,0.02646],[442,0.02018],[5712,0.0201],[311,0.01505],[2233,0.01274],[2285,0.01179],[4290,0.01174],[34222,0.01096]]],[[[530,0.01885],[61236,0.01237],[2270,0.00913],[478,0.00802],[21845,0.00738],[42814,0.00423],[15725,0.00394],[11869,0.0035],[42978,0.00349],[2002,0.00313]],[[56198,0.03582],[519,0.03301],[56166,0.0296],[403,0.02714],[307,0.0221],[56186,0.01773],[13,0.01604],[56195,0.01233],[56191,0.01174],[956,0.01069]],[[2101,0.12245],[956,0.03121],[16602,0.03068],[3193,0.02064],[293,0.02028],[334,0.01626],[427,0.01532],[9867,0.01525],[961,0.01515],[4514,0.01365]]],[[[530,0.02011],[61236,0.01316],[21845,0.00948],[2270,0.00807],[478,0.00791],[42814,0.00424],[11869,0.00404],[15725,0.00404],[2002,0.00305],[723,0.0028]],[[56198,0.10743],[519,0.08427],[56213,0.02026],[1915,0.0156],[37432,0.0149],[289,0.01315],[403,0.01291],[2196,0.00923],[56195,0.009],[307,0.00892]],[[9103,0.47486],[2434,0.1976],[2196,0.02955],[1714,0.0115],[14502,0.00936],[1216,0.00641],[6948,0.00633],[1168,0.00616],[2082,0.00577],[12368,0.00545]]],[[[956,0.04549],[56166,0.03705],[1938,0.03071],[829,0.0205],[336,0.01657],[817,0.01601],[632,0.01115],[569,0.01046],[702,0.00819],[1946,0.00728]],[[403,0.53647],[56183,0.13451],[13,0.09163],[956,0.03071],[56197,0.02862],[56186,0.0272],[56208,0.01271],[56198,0.00959],[56166,0.00853],[56213,0.00635]],[[2434,0.69171],[9103,0.27462],[2927,0.00126],[309,0.00126],[7727,0.00113],[6133,0.00107],[1168,0.001],[282,0.00078],[8436,0.00076],[293,0.00071]]]],"tgt":{"13":{"p":[[2e-06,0.0,0.0],[2.9e-05,3e-06,1.5e-05],[0.00019,2.4e-05,3e-06],[9.3e-05,0.002259,3.5e-05],[0.000161,0.003328,0.000237],[0.000158,0.016802,0.003745],[8.6e-05,0.01604,0.003169],[9.3e-05,0.003745,0.000258],[0.003214,0.091635,0.000308]],"r":[[15768,42963,38502],[4110,8700,7005],[775,4374,11086],[1609,51,2330],[630,28,523],[1022,10,36],[1959,7,35],[1810,23,154],[39,3,23]]},"403":{"p":[[0.0,1e-06,0.0],[0.000179,4e-06,8e-06],[0.000142,6e-05,0.0],[2.3e-05,0.001602,1e-06],[1.2e-05,0.002154,6.4e-05],[1.2e-05,0.030179,0.000576],[9e-06,0.027136,0.001334],[1.1e-05,0.012908,0.00013],[0.001853,0.536473,0.000104]],"r":[[44927,18485,59694],[832,7145,10376],[1122,1989,31112],[6094,78,21748],[8536,43,1641],[11905,5,216],[14420,4,98],[12758,7,321],[74,1,61]]},"956":{"p":[[0.0,0.0,0.0],[1e-06,1.9e-05,1e-06],[9e-06,1.3e-05,0.0],[3e-06,0.000436,6e-06],[3e-06,0.00026,4.3e-05],[6e-06,0.006899,0.000899],[5e-06,0.010691,0.031208],[5e-06,0.00223,0.002808],[0.045486,0.030706,0.000152]],"r":[[63727,51465,48438],[29675,2373,30068],[12883,6794,28409],[24338,329,8304],[21817,380,2276],[18394,17,148],[19882,10,2],[19816,42,17],[1,4,41]]},"1938":{"p":[[8e-06,2e-06,0.0],[2.9e-05,1e-06,0.0],[1e-05,0.0,0.0],[2e-06,4e-06,0.0],[1e-06,3e-06,1e-06],[7e-06,7.7e-05,7e-06],[7e-06,0.000125,3.6e-05],[8e-06,1e-05,0.000531],[0.030709,1.4e-05,3.2e-05]],"r":[[7187,11120,26164],[4103,17986,47447],[11870,42628,44608],[28234,14607,58654],[33838,12512,24214],[16499,1054,7052],[16099,908,1890],[15641,7130,86],[3,689,146]]},"2434":{"p":[[7.9e-05,1e-06,0.0],[3.1e-05,0.0,0.0],[4e-06,1e-06,0.0],[2e-06,1.5e-05,0.0],[1e-06,3.9e-05,0.000129],[6e-06,2.2e-05,5e-05],[6e-06,8e-06,0.001677],[6e-06,0.00044,0.197597],[8.8e-05,0.001167,0.691706]],"r":[[1464,15999,56590],[3908,44621,48377],[20303,23374,44220],[26894,6280,34402],[29686,2135,884],[18346,2762,1811],[19047,6880,77],[18048,257,2],[1252,27,1]]},"6133":{"p":[[2e-06,1e-06,0.0],[2.3e-05,2e-06,5e-06],[3e-05,5.9e-05,1.5e-05],[6e-06,0.00016,0.0],[4e-06,0.001315,1e-06],[2e-06,0.002842,1e-05],[2e-06,0.000123,2.3e-05],[2e-06,0.000141,0.001641],[0.000585,7e-05,0.001068]],"r":[[15345,19622,55570],[4889,10858,14133],[5295,2016,4296],[15609,936,26326],[18048,68,17940],[32404,39,5528],[33886,925,2544],[32119,782,28],[255,201,6]]},"9103":{"p":[[0.000133,1e-06,0.0],[0.000117,1e-06,8e-06],[5.2e-05,7e-05,8e-06],[8e-05,0.000258,0.0],[1.2e-05,0.000248,2.4e-05],[2.8e-05,0.00037,7.3e-05],[3.6e-05,4.5e-05,0.000619],[4.4e-05,0.000764,0.474863],[0.000907,0.001811,0.274622]],"r":[[956,18345,32784],[1280,13820,10512],[3213,1734,6800],[1883,542,29736],[8335,399,3463],[5994,258,1361],[4809,2115,191],[3891,137,1],[159,19,2]]},"56166":{"p":[[3e-06,3e-06,1e-06],[0.001454,1.2e-05,0.000194],[0.000557,1.1e-05,1e-06],[5.9e-05,0.000943,7.4e-05],[2.7e-05,0.001828,2.3e-05],[9.8e-05,0.012203,0.000562],[6.1e-05,0.029596,0.002309],[5.7e-05,0.00125,0.000168],[0.037049,0.008532,0.000263]],"r":[[11978,9095,22573],[86,3181,606],[223,7978,19998],[2586,147,1302],[4284,54,3541],[1720,13,222],[2770,3,53],[2988,81,240],[2,9,28]]},"56183":{"p":[[7e-06,4e-06,0.0],[0.000884,1.6e-05,6e-06],[7.7e-05,4.8e-05,1e-06],[3.8e-05,0.005117,3e-06],[3.7e-05,0.005867,1.3e-05],[3.3e-05,0.045562,0.001861],[2.4e-05,0.01066,0.000693],[2.3e-05,0.004911,2.4e-05],[0.002148,0.134508,0.000222]],"r":[[8049,8289,56926],[146,2735,12969],[2191,2421,20993],[3991,15,11324],[3158,15,5201],[5239,4,86],[6747,11,171],[7234,18,1231],[60,2,34]]}}}}}